Workbook
Name IQ_CH: 110000
Name IQ_CQ: 5000
Name IQ_CY: 10000
Name IQ_DAILY: 500000
Name IQ_FH: 100000
Name IQ_FQ: 500
Name IQ_FY: 1000
Name IQ_LTM: 2000
Name IQ_MONTH: 15000
Name IQ_NTM: 6000
Name IQ_WEEK: 50000
Name IQ_YTD: 3000

Sheet Trajectory
A1: AI Capex / Revenue Proxy and Forward ROIC — Filing-Based Reconstruction
A2: Public facts are linked in notes. AI attribution, duration and margins are assumptions. Spread is shown in percentage points; only the change row on Snapshot is basis points.
A4: Company | B4: Metric | C4: Q2 25 | D4: Q3 25 | E4: Q4 25 | F4: Q1 26 | G4: Q2 26
A5: MSFT | B5: Commercial RPO/Backlog ($B) | C5: =Inputs!$F$5 -> 368 | D5: =Inputs!$F$6 -> 392 | E5: =Inputs!$F$7 -> 625 | F5: =Inputs!$F$8 -> 627 | G5: =Inputs!$F$9 -> 678
B6: Quarterly Capex ($B) | C6: =Inputs!$H$5 -> 24.2 | D6: =Inputs!$H$6 -> 34.9 | E6: =Inputs!$H$7 -> 37.5 | F6: =Inputs!$H$8 -> 31.9 | G6: =Inputs!$H$9 -> 41
B7: Annualized AI Capex ($B) | C7: =C6*4*Inputs!$T$5 -> 82.28 | D7: =D6*4*Inputs!$T$5 -> 118.66 | E7: =E6*4*Inputs!$T$5 -> 127.5 | F7: =F6*4*Inputs!$T$5 -> 108.46 | G7: =G6*4*Inputs!$T$5 -> 139.4
B8: Annualized AI Revenue Proxy ($B) | C8: =C5*Inputs!$R$5/Inputs!$S$5 -> 73.6 | D8: =D5*Inputs!$R$5/Inputs!$S$5 -> 78.4 | E8: =E5*Inputs!$R$5/Inputs!$S$5 -> 125 | F8: =F5*Inputs!$R$5/Inputs!$S$5 -> 125.4 | G8: =G5*Inputs!$R$5/Inputs!$S$5 -> 135.6
B9: Forward ROIC (Base) | C9: =C8*Inputs!$V$5/C7 -> 0.26835197 | D9: =D8*Inputs!$V$5/D7 -> 0.19821338 | E9: =E8*Inputs!$V$5/E7 -> 0.29411765 | F9: =F8*Inputs!$V$5/F7 -> 0.34685598 | G9: =G8*Inputs!$V$5/G7 -> 0.29182209
B10: Spread vs WACC (ppt) | C10: =C9-Inputs!$X$5 -> 0.17495197 | D10: =D9-Inputs!$X$5 -> 0.10481338 | E10: =E9-Inputs!$X$5 -> 0.20071765 | F10: =F9-Inputs!$X$5 -> 0.25345598 | G10: =G9-Inputs!$X$5 -> 0.19842209
A12: GOOG | B12: Revenue Backlog/RPO ($B) | C12: =Inputs!$F$10 -> 108.2 | D12: =Inputs!$F$11 -> 157.7 | E12: =Inputs!$F$12 -> 242.8 | F12: =Inputs!$F$13 -> 467.6 | G12: =Inputs!$F$14 -> 519.5
B13: Quarterly Capex ($B) | C13: =Inputs!$H$10 -> 22.446 | D13: =Inputs!$H$11 -> 23.953 | E13: =Inputs!$H$12 -> 27.851 | F13: =Inputs!$H$13 -> 35.674 | G13: =Inputs!$H$14 -> 44.924
B14: Annualized AI Capex ($B) | C14: =C13*4*Inputs!$T$6 -> 71.8272 | D14: =D13*4*Inputs!$T$6 -> 76.6496 | E14: =E13*4*Inputs!$T$6 -> 89.1232 | F14: =F13*4*Inputs!$T$6 -> 114.1568 | G14: =G13*4*Inputs!$T$6 -> 143.7568
B15: Annualized AI Revenue Proxy ($B) | C15: =C12*Inputs!$R$6/Inputs!$S$6 -> 28.132 | D15: =D12*Inputs!$R$6/Inputs!$S$6 -> 41.002 | E15: =E12*Inputs!$R$6/Inputs!$S$6 -> 63.128 | F15: =F12*Inputs!$R$6/Inputs!$S$6 -> 121.576 | G15: =G12*Inputs!$R$6/Inputs!$S$6 -> 135.07
B16: Forward ROIC (Base) | C16: =C15*Inputs!$V$6/C14 -> 0.11749866 | D16: =D15*Inputs!$V$6/D14 -> 0.16047833 | E16: =E15*Inputs!$V$6/E14 -> 0.21249686 | F16: =F15*Inputs!$V$6/F14 -> 0.31949739 | G16: =G15*Inputs!$V$6/G14 -> 0.28187188
B17: Spread vs WACC (ppt) | C17: =C16-Inputs!$X$6 -> 0.010898663 | D17: =D16-Inputs!$X$6 -> 0.053878333 | E17: =E16-Inputs!$X$6 -> 0.10589686 | F17: =F16-Inputs!$X$6 -> 0.21289739 | G17: =G16-Inputs!$X$6 -> 0.17527188
A19: AMZN | B19: AWS-linked Commitments/RPO ($B) | C19: =Inputs!$F$15 -> 195 | D19: =Inputs!$F$16 -> 200 | E19: =Inputs!$F$17 -> 244 | F19: =Inputs!$F$18 -> 364 | G19: =Inputs!$F$19 -> 496
B20: Quarterly Capex ($B) | C20: =Inputs!$H$15 -> 32.183 | D20: =Inputs!$H$16 -> 35.095 | E20: =Inputs!$H$17 -> 39.522 | F20: =Inputs!$H$18 -> 44.203 | G20: =Inputs!$H$19 -> 54.208
B21: Annualized AI Capex ($B) | C21: =C20*4*Inputs!$T$7 -> 96.549 | D21: =D20*4*Inputs!$T$7 -> 105.285 | E21: =E20*4*Inputs!$T$7 -> 118.566 | F21: =F20*4*Inputs!$T$7 -> 132.609 | G21: =G20*4*Inputs!$T$7 -> 162.624
B22: Annualized AI Revenue Proxy ($B) | C22: =C19*Inputs!$R$7/Inputs!$S$7 -> 26.8125 | D22: =D19*Inputs!$R$7/Inputs!$S$7 -> 27.5 | E22: =E19*Inputs!$R$7/Inputs!$S$7 -> 33.55 | F22: =F19*Inputs!$R$7/Inputs!$S$7 -> 50.05 | G22: =G19*Inputs!$R$7/Inputs!$S$7 -> 68.2
B23: Forward ROIC (Base) | C23: =C22*Inputs!$V$7/C21 -> 0.077758444 | D23: =D22*Inputs!$V$7/D21 -> 0.073134825 | E23: =E22*Inputs!$V$7/E21 -> 0.079230133 | F23: =F22*Inputs!$V$7/F21 -> 0.1056791 | G23: =G22*Inputs!$V$7/G21 -> 0.11742424
B24: Spread vs WACC (ppt) | C24: =C23-Inputs!$X$7 -> 0.0050584439 | D24: =D23-Inputs!$X$7 -> 0.00043482452 | E24: =E23-Inputs!$X$7 -> 0.0065301334 | F24: =F23-Inputs!$X$7 -> 0.032979102 | G24: =G23-Inputs!$X$7 -> 0.044724242
A26: ORCL | B26: RPO ($B) | C26: =Inputs!$F$20 -> 137.8 | D26: =Inputs!$F$21 -> 455.3 | E26: =Inputs!$F$22 -> 523.3 | F26: =Inputs!$F$23 -> 552.6 | G26: =Inputs!$F$24 -> 638
B27: Quarterly Capex ($B) | C27: =Inputs!$H$20 -> 9.08 | D27: =Inputs!$H$21 -> 8.502 | E27: =Inputs!$H$22 -> 12.033 | F27: =Inputs!$H$23 -> 18.635 | G27: =Inputs!$H$24 -> 16.493
B28: Annualized AI Capex ($B) | C28: =C27*4*Inputs!$T$8 -> 32.688 | D28: =D27*4*Inputs!$T$8 -> 30.6072 | E28: =E27*4*Inputs!$T$8 -> 43.3188 | F28: =F27*4*Inputs!$T$8 -> 67.086 | G28: =G27*4*Inputs!$T$8 -> 59.3748
B29: Annualized AI Revenue Proxy ($B) | C29: =C26*Inputs!$R$8/Inputs!$S$8 -> 23.426 | D29: =D26*Inputs!$R$8/Inputs!$S$8 -> 77.401 | E29: =E26*Inputs!$R$8/Inputs!$S$8 -> 88.961 | F29: =F26*Inputs!$R$8/Inputs!$S$8 -> 93.942 | G29: =G26*Inputs!$R$8/Inputs!$S$8 -> 108.46
B30: Forward ROIC (Base) | C30: =C29*Inputs!$V$8/C28 -> 0.1289978 | D30: =D29*Inputs!$V$8/D28 -> 0.4551929 | E30: =E29*Inputs!$V$8/E28 -> 0.36965428 | F30: =F29*Inputs!$V$8/F28 -> 0.25205796 | G30: =G29*Inputs!$V$8/G28 -> 0.32880616
B31: Spread vs WACC (ppt) | C31: =C30-Inputs!$X$8 -> 0.050697797 | D31: =D30-Inputs!$X$8 -> 0.3768929 | E31: =E30-Inputs!$X$8 -> 0.29135428 | F31: =F30-Inputs!$X$8 -> 0.17375796 | G31: =G30-Inputs!$X$8 -> 0.25050616
A33: META | B33: Revenue (Quarter, $B) | C33: =Inputs!$F$25 -> 47.516 | D33: =Inputs!$F$26 -> 51.242 | E33: =Inputs!$F$27 -> 59.893 | F33: =Inputs!$F$28 -> 56.311 | G33: =Inputs!$F$29 -> 60.801
B34: Quarterly Capex ($B) | C34: =Inputs!$H$25 -> 17.012 | D34: =Inputs!$H$26 -> 19.374 | E34: =Inputs!$H$27 -> 22.137 | F34: =Inputs!$H$28 -> 19.84 | G34: =Inputs!$H$29 -> 31.078
B35: Annualized AI Capex ($B) | C35: =C34*4*Inputs!$T$9 -> 61.2432 | D35: =D34*4*Inputs!$T$9 -> 69.7464 | E35: =E34*4*Inputs!$T$9 -> 79.6932 | F35: =F34*4*Inputs!$T$9 -> 71.424 | G35: =G34*4*Inputs!$T$9 -> 111.8808
B36: Annualized AI Revenue Proxy ($B) | C36: =C33*4*Inputs!$R$9 -> 38.0128 | D36: =D33*4*Inputs!$R$9 -> 40.9936 | E36: =E33*4*Inputs!$R$9 -> 47.9144 | F36: =F33*4*Inputs!$R$9 -> 45.0488 | G36: =G33*4*Inputs!$R$9 -> 48.6408
B37: Forward ROIC (Base) | C37: =C36*Inputs!$V$9/C35 -> 0.19861954 | D37: =D36*Inputs!$V$9/D35 -> 0.1880807 | E37: =E36*Inputs!$V$9/E35 -> 0.19239544 | F37: =F36*Inputs!$V$9/F35 -> 0.20183154 | G37: =G36*Inputs!$V$9/G35 -> 0.13912178
B38: Spread vs WACC (ppt) | C38: =C37-Inputs!$X$9 -> 0.092019537 | D38: =D37-Inputs!$X$9 -> 0.081480704 | E38: =E37-Inputs!$X$9 -> 0.085795436 | F38: =F37-Inputs!$X$9 -> 0.095231541 | G38: =G37-Inputs!$X$9 -> 0.03252178

Sheet Snapshot
A1: Latest-Quarter Forward ROIC Snapshot — Filing-Based Reconstruction
A3: Metric | B3: MSFT | C3: GOOG | D3: AMZN | E3: ORCL | F3: META
A4: Latest Quarter | B4: FY26 Q4 (Jun. 30, 2026) | C4: Q2 2026 (Jun. 30, 2026) | D4: Q2 2026 (Jun. 30, 2026) | E4: FY26 Q4 (May. 31, 2026) | F4: Q2 2026 (Jun. 30, 2026)
A5: AI Revenue Source | B5: Commercial RPO × assumed AI share ÷ assumed duration | C5: RPO × assumed AI share ÷ assumed duration | D5: RPO × assumed AI share ÷ assumed duration | E5: RPO × assumed AI share ÷ assumed duration | F5: Quarterly revenue × 4 × assumed AI attribution
A6: Total RPO/Backlog or Annualized Revenue ($B) | B6: =Inputs!$F$9 -> 678 | C6: =Inputs!$F$14 -> 519.5 | D6: =Inputs!$F$19 -> 496 | E6: =Inputs!$F$24 -> 638 | F6: =Inputs!$F$29*4 -> 243.204
A7: AI Share % (assumption) | B7: =Inputs!$R$5 -> 0.5 | C7: =Inputs!$R$6 -> 0.65 | D7: =Inputs!$R$7 -> 0.55 | E7: =Inputs!$R$8 -> 0.85 | F7: =Inputs!$R$9 -> 0.2
A8: AI-linked RPO/Revenue ($B) | B8: =B6*B7 -> 339 | C8: =C6*C7 -> 337.675 | D8: =D6*D7 -> 272.8 | E8: =E6*E7 -> 542.3 | F8: =F6*F7 -> 48.6408
A9: Annual Capex Guide / Midpoint / Actual ($B) | B9: =Inputs!$Z$5 -> 175 | C9: =Inputs!$Z$6 -> 200 | D9: =Inputs!$Z$7 -> 200 | E9: =Inputs!$Z$8 -> 55.663 | F9: =Inputs!$Z$9 -> 137.5
A10: Plan Basis | B10: =Inputs!$AA$5 -> CY2026 reported capex outlook after FY26 Q4 results | C10: =Inputs!$AA$6 -> Midpoint of updated CY2026 $195B-$205B company range | D10: =Inputs!$AA$7 -> CY2026 company outlook; no replacement numeric Q2 update | E10: =Inputs!$AA$8 -> FY2026 reported actual; no comparable FY2027 gross-capex guide | F10: =Inputs!$AA$9 -> Midpoint of narrowed CY2026 $130B-$145B company range
A11: AI Share of Capex % (assumption) | B11: =Inputs!$T$5 -> 0.85 | C11: =Inputs!$T$6 -> 0.8 | D11: =Inputs!$T$7 -> 0.75 | E11: =Inputs!$T$8 -> 0.9 | F11: =Inputs!$T$9 -> 0.9
A12: AI Capex ($B) | B12: =B9*B11 -> 148.75 | C12: =C9*C11 -> 160 | D12: =D9*D11 -> 150 | E12: =E9*E11 -> 50.0967 | F12: =F9*F11 -> 123.75
A13: RPO Duration (years, assumption) | B13: =Inputs!$S$5 -> 2.5 | C13: =Inputs!$S$6 -> 2.5 | D13: =Inputs!$S$7 -> 4 | E13: =Inputs!$S$8 -> 5 | F13: N/A
A14: Annualized AI Revenue Proxy ($B) | B14: =B8/B13 -> 135.6 | C14: =C8/C13 -> 135.07 | D14: =D8/D13 -> 68.2 | E14: =E8/E13 -> 108.46 | F14: =F8 -> 48.6408
A15: NOPAT Margin (Base) | B15: =Inputs!$V$5 -> 0.3 | C15: =Inputs!$V$6 -> 0.3 | D15: =Inputs!$V$7 -> 0.28 | E15: =Inputs!$V$8 -> 0.18 | F15: =Inputs!$V$9 -> 0.32
A16: — SNAPSHOT VIEW (latest annual capex denominator) —
A17: Forward ROIC (Base) | B17: =B14*Inputs!$V$5/B12 -> 0.27347899 | C17: =C14*Inputs!$V$6/C12 -> 0.25325625 | D17: =D14*Inputs!$V$7/D12 -> 0.12730667 | E17: =E14*Inputs!$V$8/E12 -> 0.38970232 | F17: =F14*Inputs!$V$9/F12 -> 0.12577823
A18: WACC (Damodaran sector, Jan. 2026) | B18: =Inputs!$X$5 -> 0.0934 | C18: =Inputs!$X$6 -> 0.1066 | D18: =Inputs!$X$7 -> 0.0727 | E18: =Inputs!$X$8 -> 0.0783 | F18: =Inputs!$X$9 -> 0.1066
A19: Spread (Base, ppt) | B19: =B17-B18 -> 0.18007899 | C19: =C17-C18 -> 0.14665625 | D19: =D17-D18 -> 0.054606667 | E19: =E17-E18 -> 0.31140232 | F19: =F17-F18 -> 0.01917823
A20: Forward ROIC (Bear) | B20: =B14*Inputs!$U$5/B12 -> 0.18231933 | C20: =C14*Inputs!$U$6/C12 -> 0.1688375 | D20: =D14*Inputs!$U$7/D12 -> 0.090933333 | E20: =E14*Inputs!$U$8/E12 -> 0.21650129 | F20: =F14*Inputs!$U$9/F12 -> 0.098264242
A21: Spread (Bear, ppt) | B21: =B20-B18 -> 0.088919328 | C21: =C20-C18 -> 0.0622375 | D21: =D20-D18 -> 0.018233333 | E21: =E20-E18 -> 0.13820129 | F21: =F20-F18 -> -0.0083357576
A22: Forward ROIC (Bull) | B22: =B14*Inputs!$W$5/B12 -> 0.36463866 | C22: =C14*Inputs!$W$6/C12 -> 0.337675 | D22: =D14*Inputs!$W$7/D12 -> 0.17277333 | E22: =E14*Inputs!$W$8/E12 -> 0.54125322 | F22: =F14*Inputs!$W$9/F12 -> 0.15722279
A23: Spread (Bull, ppt) | B23: =B22-B18 -> 0.27123866 | C23: =C22-C18 -> 0.231075 | D23: =D22-D18 -> 0.10007333 | E23: =E22-E18 -> 0.46295322 | F23: =F22-F18 -> 0.050622788
A24: — TRAJECTORY VIEW (quarterly capex × 4 as denominator) —
A25: Spread Q2 26 (run-rate basis, ppt) | B25: =Trajectory!$G$10 -> 0.19842209 | C25: =Trajectory!$G$17 -> 0.17527188 | D25: =Trajectory!$G$24 -> 0.044724242 | E25: =Trajectory!$G$31 -> 0.25050616 | F25: =Trajectory!$G$38 -> 0.03252178
A26: Spread Q2 25 (run-rate basis, ppt) | B26: =Trajectory!$C$10 -> 0.17495197 | C26: =Trajectory!$C$17 -> 0.010898663 | D26: =Trajectory!$C$24 -> 0.0050584439 | E26: =Trajectory!$C$31 -> 0.050697797 | F26: =Trajectory!$C$38 -> 0.092019537
A27: Δ Spread Q2 26 vs Q2 25 (bps) | B27: =(B25-B26)*10000 -> 234.70126 | C27: =(C25-C26)*10000 -> 1643.7322 | D27: =(D25-D26)*10000 -> 396.65799 | E27: =(E25-E26)*10000 -> 1998.0836 | F27: =(F25-F26)*10000 -> -594.97757

Sheet Inputs
A1: Filing Inputs | P1: Model Assumptions and Latest Annual Capex Denominators
A2: Blue cells are public-filing or official-company facts. Yellow cells are analyst assumptions. Every sourced value carries a cell note with the public URL.
A4: Company | B4: Ticker | C4: Report Bucket | D4: Fiscal Period | E4: Period End | F4: RPO/Backlog or Revenue ($B) | G4: Fact Metric | H4: Quarterly Capex ($B) | I4: Capex Definition | J4: Fact Source URL | K4: Capex Source URL | L4: Evidence / Derivation | M4: Fact Source ID | N4: Capex Source ID | P4: Ticker | Q4: AI Revenue Proxy | R4: AI Share of RPO/Revenue | S4: RPO Duration (Years) | T4: AI Share of Capex | U4: NOPAT Margin (Bear) | V4: NOPAT Margin (Base) | W4: NOPAT Margin (Bull) | X4: WACC | Y4: Damodaran Sector / Date | Z4: Annual Capex Guide / Midpoint / Actual ($B) | AA4: Plan Basis | AB4: Plan Source URL | AC4: Source / Assumption Caveat
A5: Microsoft | B5: MSFT | C5: Q2 25 | D5: FY25 Q4 | E5: 45838 | F5: 368 | G5: Commercial remaining performance obligation | H5: 24.2 | I5: Company-reported capex, including finance leases | J5: https://www.sec.gov/Archives/edgar/data/789019/000095017025100235/msft-20250630.htm | K5: https://www.microsoft.com/en-us/Investor/earnings/FY-2025-Q4/press-release-webcast | L5: Fact: Commercial RPO increased to $368B at June 30, 2025. Capex: Official FY25 Q4 transcript: capital expenditures were $24.2B, including finance leases. | M5: MSFT-Q225-FACT | N5: MSFT-Q225-CAPEX | P5: MSFT | Q5: Commercial RPO × assumed AI share ÷ assumed duration | R5: 0.5 | S5: 2.5 | T5: 0.85 | U5: 0.2 | V5: 0.3 | W5: 0.4 | X5: 0.0934 | Y5: Software (System & Application), January 2026 U.S. industry average | Z5: 175 | AA5: CY2026 reported capex outlook after FY26 Q4 results | AB5: https://www.microsoft.com/en-us/investor/events/fy-2026/earnings-fy-2026-q4 | AC5: Microsoft reduced reported CY2026 capex expectation to approximately $175B from roughly $190B because longer datacenter useful lives shift future leases from finance leases included in its capex metric to operating leases excluded from it. Management said underlying investment expectations were unchanged; the lower denominator is a classification effect. AI share, 2.5-year duration, and scenario margins retain the supplied model assumptions for comparability. Microsoft disclosed a 2.3-year weighted-average commercial-RPO duration including OpenAI at June 30, 2026; using 2.3 years would be a methodology change.
A6: Microsoft | B6: MSFT | C6: Q3 25 | D6: FY26 Q1 | E6: 45930 | F6: 392 | G6: Commercial remaining performance obligation | H6: 34.9 | I6: Company-reported capex, including finance-lease timing effects | J6: https://www.sec.gov/Archives/edgar/data/789019/000119312525256321/msft-20250930.htm | K6: https://www.microsoft.com/en-us/Investor/earnings/FY-2026-Q1/press-release-webcast | L6: Fact: The 10-Q reports $398B total RPO, of which $392B is commercial RPO. Capex: Official FY26 Q1 transcript: capital expenditures were $34.9B. | M6: MSFT-Q325-FACT | N6: MSFT-Q325-CAPEX | P6: GOOG | Q6: RPO × assumed AI share ÷ assumed duration | R6: 0.65 | S6: 2.5 | T6: 0.8 | U6: 0.2 | V6: 0.3 | W6: 0.4 | X6: 0.1066 | Y6: Software (Internet), January 2026 U.S. industry average | Z6: 200 | AA6: Midpoint of updated CY2026 $195B-$205B company range | AB6: https://abc.xyz/investor/events/event-details/2026/2026-Q2-Earnings-Call-2026-GgTAq7Is0z/default.aspx | AC6: Alphabet's official Q2 2026 call raised its 2026 capex range to $195B-$205B from $180B-$190B. $200B is the model midpoint, not company point guidance. AI share, 2.5-year duration, and scenario margins retain the supplied model assumptions. Alphabet says just over half of backlog should be recognized over 24 months but does not disclose a single average duration or a 65% AI share.
A7: Microsoft | B7: MSFT | C7: Q4 25 | D7: FY26 Q2 | E7: 46022 | F7: 625 | G7: Commercial remaining performance obligation | H7: 37.5 | I7: Company-reported capex, including finance-lease timing effects | J7: https://www.sec.gov/Archives/edgar/data/789019/000119312526027207/msft-20251231.htm | K7: https://www.microsoft.com/en-us/Investor/earnings/FY-2026-Q2/press-release-webcast | L7: Fact: Commercial RPO was $625B with a weighted-average duration of approximately 2.5 years. Capex: Official FY26 Q2 transcript: capital expenditures were $37.5B. | M7: MSFT-Q425-FACT | N7: MSFT-Q425-CAPEX | P7: AMZN | Q7: RPO × assumed AI share ÷ assumed duration | R7: 0.55 | S7: 4 | T7: 0.75 | U7: 0.2 | V7: 0.28 | W7: 0.38 | X7: 0.0727 | Y7: Retail (General), January 2026 U.S. industry average | Z7: 200 | AA7: CY2026 company outlook; no replacement numeric Q2 update | AB7: https://www.sec.gov/Archives/edgar/data/1018724/000101872426000002/amzn-20251231xex991.htm | AC7: Amazon's SEC-filed Q4 2025 release said it expected about $200B of 2026 capex. The Q2 2026 10-Q and filed release did not provide a replacement numeric full-year plan. AI share, four-year duration, and scenario margins retain the supplied model assumptions for comparability. Amazon disclosed a 6.4-year weighted-average remaining contract life at June 30, 2026; the four-year model input materially accelerates the annualized revenue proxy.
A8: Microsoft | B8: MSFT | C8: Q1 26 | D8: FY26 Q3 | E8: 46112 | F8: 627 | G8: Commercial remaining performance obligation | H8: 31.9 | I8: Company-reported capex, including finance-lease timing effects | J8: https://www.sec.gov/Archives/edgar/data/789019/000119312526191507/msft-20260331.htm | K8: https://www.microsoft.com/en-us/Investor/earnings/FY-2026-Q3/press-release-webcast | L8: Fact: Commercial RPO was $627B with a weighted-average duration of approximately 2.5 years. Capex: Official FY26 Q3 transcript: capital expenditures were $31.9B; cash paid for PP&E was $30.9B. | M8: MSFT-Q126-FACT | N8: MSFT-Q126-CAPEX | P8: ORCL | Q8: RPO × assumed AI share ÷ assumed duration | R8: 0.85 | S8: 5 | T8: 0.9 | U8: 0.1 | V8: 0.18 | W8: 0.25 | X8: 0.0783 | Y8: Computer Services, January 2026 U.S. industry average | Z8: 55.663 | AA8: FY2026 reported actual; no comparable FY2027 gross-capex guide | AB8: https://www.sec.gov/Archives/edgar/data/1341439/000119312526265848/orcl-ex99_1.htm | AC8: Oracle reported FY2026 GAAP cash capex of $55.663B. Official Q4 slides guide to approximately $70B of FY2027 net cash outlay for capex, a non-GAAP measure that deducts capex financing and customer prepayments and is not interchangeable with gross capex. The model uses the latest completed gross-capex actual rather than the expired $50B FY2026 outlook. Official slides: https://s23.q4cdn.com/440135859/files/doc_financials/2026/q4/Q4-FY26-Oracle-Earnings-Slides.pdf. Local backup: 01_sources/company_filings/oracle/Oracle_2026-06-10_Q4-FY26_Earnings_Slides.pdf AI shares, five-year duration, and scenario margins retain the supplied model assumptions. Oracle reports company-wide RPO and does not disclose that 85% is AI or that recognition is straight-line over five years.
A9: Microsoft | B9: MSFT | C9: Q2 26 | D9: FY26 Q4 | E9: 46203 | F9: 678 | G9: Commercial remaining performance obligation | H9: 41 | I9: Management-reported capex, including finance-lease commencement effects | J9: https://www.sec.gov/Archives/edgar/data/789019/000119312526323660/msft-20260630.htm | K9: https://www.microsoft.com/en-us/investor/events/fy-2026/earnings-fy-2026-q4 | L9: Fact: Commercial remaining performance obligation was $678B; total company RPO was $684B. Weighted-average commercial-RPO duration including OpenAI was 2.3 years. Capex: Official FY26 Q4 call reports management capex of $41.0B, including $5.6B of finance leases; cash paid for PP&E was $35.8B. The trajectory preserves Microsoft's management capex series. | M9: MSFT-Q226-FACT | N9: MSFT-Q226-CAPEX | P9: META | Q9: Quarterly revenue × 4 × assumed AI attribution | R9: 0.2 | T9: 0.9 | U9: 0.25 | V9: 0.32 | W9: 0.4 | X9: 0.1066 | Y9: Software (Internet), January 2026 U.S. industry average | Z9: 137.5 | AA9: Midpoint of narrowed CY2026 $130B-$145B company range | AB9: https://www.sec.gov/Archives/edgar/data/1326801/000162828026050596/meta-06302026xexhibit991.htm | AC9: Meta narrowed 2026 capex guidance to $130B-$145B from $125B-$145B. $137.5B is the model midpoint, not company point guidance. The 20% AI revenue attribution, 90% AI capex share, and scenario margins retain the supplied model assumptions. Meta does not report standalone AI revenue or AI-only capex.
A10: Alphabet | B10: GOOG | C10: Q2 25 | D10: Q2 2025 | E10: 45838 | F10: 108.2 | G10: Revenue backlog / remaining performance obligations | H10: 22.446 | I10: Cash purchases of property and equipment | J10: https://www.sec.gov/Archives/edgar/data/1652044/000165204425000062/goog-20250630.htm | K10: https://www.sec.gov/Archives/edgar/data/1652044/000165204425000062/goog-20250630.htm | L10: Fact: Revenue backlog/RPO was $108.2B as of June 30, 2025. Capex: Quarter capex = $39.643B first-half cash PP&E purchases less $17.197B Q1 = $22.446B. | M10: GOOG-Q225-FACT | N10: GOOG-Q225-CAPEX
A11: Alphabet | B11: GOOG | C11: Q3 25 | D11: Q3 2025 | E11: 45930 | F11: 157.7 | G11: Revenue backlog / remaining performance obligations | H11: 23.953 | I11: Cash purchases of property and equipment | J11: https://www.sec.gov/Archives/edgar/data/1652044/000165204425000091/goog-20250930.htm | K11: https://www.sec.gov/Archives/edgar/data/1652044/000165204425000091/goog-20250930.htm | L11: Fact: Revenue backlog/RPO was $157.7B as of September 30, 2025, primarily related to Google Cloud. Capex: Quarter capex = $63.596B nine-month cash PP&E purchases less $39.643B first half = $23.953B. | M11: GOOG-Q325-FACT | N11: GOOG-Q325-CAPEX
A12: Alphabet | B12: GOOG | C12: Q4 25 | D12: Q4 2025 | E12: 46022 | F12: 242.8 | G12: Revenue backlog / remaining performance obligations | H12: 27.851 | I12: Cash purchases of property and equipment | J12: https://www.sec.gov/Archives/edgar/data/1652044/000165204426000018/goog-20251231.htm | K12: https://www.sec.gov/Archives/edgar/data/1652044/000165204426000018/goog-20251231.htm | L12: Fact: Revenue backlog/RPO was $242.8B as of December 31, 2025, primarily related to Google Cloud. Capex: Quarter capex = $91.447B FY2025 cash PP&E purchases less $63.596B first nine months = $27.851B. | M12: GOOG-Q425-FACT | N12: GOOG-Q425-CAPEX
A13: Alphabet | B13: GOOG | C13: Q1 26 | D13: Q1 2026 | E13: 46112 | F13: 467.6 | G13: Revenue backlog / remaining performance obligations | H13: 35.674 | I13: Cash purchases of property and equipment | J13: https://www.sec.gov/Archives/edgar/data/1652044/000165204426000048/goog-20260331.htm | K13: https://www.sec.gov/Archives/edgar/data/1652044/000165204426000048/goog-20260331.htm | L13: Fact: Revenue backlog/RPO was $467.6B; $462.3B related to Google Cloud. Alphabet changed the definition in Q1 2026 to include original terms of one year or less ($7.3B), so the series has a comparability break. Capex: The Q1 2026 10-Q reports $35.674B of cash purchases of property and equipment. | M13: GOOG-Q126-FACT | N13: GOOG-Q126-CAPEX
A14: Alphabet | B14: GOOG | C14: Q2 26 | D14: Q2 2026 | E14: 46203 | F14: 519.5 | G14: Revenue backlog / remaining performance obligations | H14: 44.924 | I14: Cash purchases of property and equipment | J14: https://www.sec.gov/Archives/edgar/data/1652044/000165204426000071/goog-20260630.htm | K14: https://www.sec.gov/Archives/edgar/data/1652044/000165204426000071/goog-20260630.htm | L14: Fact: Revenue backlog/RPO was $519.5B, including $513.9B related to Google Cloud. The Q1 2026 short-term-contract definition change remains in effect, and Cloud backlog now includes TPU system-sale agreements; the vast majority remains GCP agreements. Capex: The Q2 2026 10-Q reports exact cash purchases of PP&E of $44.924B; narrative disclosure rounds to $44.9B. | M14: GOOG-Q226-FACT | N14: GOOG-Q226-CAPEX
A15: Amazon | B15: AMZN | C15: Q2 25 | D15: Q2 2025 | E15: 45838 | F15: 195 | G15: Long-term customer commitments, primarily AWS | H15: 32.183 | I15: Cash payments to acquire productive assets (SEC XBRL) | J15: https://www.sec.gov/Archives/edgar/data/1018724/000101872425000086/amzn-20250630.htm | K15: https://www.sec.gov/Archives/edgar/data/1018724/000101872425000086/amzn-20250630.htm | L15: Fact: Long-term customer commitments, primarily AWS, were approximately $195B as of June 30, 2025. Capex: SEC XBRL PaymentsToAcquireProductiveAssets for Q2 2025 was $32.183B. | M15: AMZN-Q225-FACT | N15: AMZN-Q225-CAPEX
A16: Amazon | B16: AMZN | C16: Q3 25 | D16: Q3 2025 | E16: 45930 | F16: 200 | G16: Long-term customer commitments, primarily AWS | H16: 35.095 | I16: Cash payments to acquire productive assets (SEC XBRL) | J16: https://www.sec.gov/Archives/edgar/data/1018724/000101872425000123/amzn-20250930.htm | K16: https://www.sec.gov/Archives/edgar/data/1018724/000101872425000123/amzn-20250930.htm | L16: Fact: Long-term customer commitments, primarily AWS, were approximately $200B; weighted-average remaining life was 3.8 years. Capex: SEC XBRL PaymentsToAcquireProductiveAssets for Q3 2025 was $35.095B. | M16: AMZN-Q325-FACT | N16: AMZN-Q325-CAPEX
A17: Amazon | B17: AMZN | C17: Q4 25 | D17: Q4 2025 | E17: 46022 | F17: 244 | G17: Long-term customer commitments, primarily AWS | H17: 39.522 | I17: Cash payments to acquire productive assets (SEC XBRL) | J17: https://www.sec.gov/Archives/edgar/data/1018724/000101872426000004/amzn-20251231.htm | K17: https://www.sec.gov/Archives/edgar/data/1018724/000101872426000004/amzn-20251231.htm | L17: Fact: Long-term customer commitments, primarily AWS, were approximately $244B as of December 31, 2025. Capex: Quarter capex = $131.819B FY2025 less $92.297B first nine months = $39.522B. | M17: AMZN-Q425-FACT | N17: AMZN-Q425-CAPEX
A18: Amazon | B18: AMZN | C18: Q1 26 | D18: Q1 2026 | E18: 46112 | F18: 364 | G18: Long-term customer commitments, primarily AWS | H18: 44.203 | I18: Cash payments to acquire productive assets (SEC XBRL) | J18: https://www.sec.gov/Archives/edgar/data/1018724/000101872426000014/amzn-20260331.htm | K18: https://www.sec.gov/Archives/edgar/data/1018724/000101872426000014/amzn-20260331.htm | L18: Fact: Long-term customer commitments, primarily AWS, were approximately $364B as of March 31, 2026—not $464B as shown in the supplied snapshot. Weighted-average remaining life was 5.5 years. Capex: SEC XBRL PaymentsToAcquireProductiveAssets was $44.203B. Amazon's narrative cash-capex measure was $43.2B; this model uses the standardized XBRL series consistently across quarters. | M18: AMZN-Q126-FACT | N18: AMZN-Q126-CAPEX
A19: Amazon | B19: AMZN | C19: Q2 26 | D19: Q2 2026 | E19: 46203 | F19: 496 | G19: Long-term customer commitments, primarily AWS | H19: 54.208 | I19: Cash payments to acquire productive assets (SEC XBRL gross series) | J19: https://www.sec.gov/Archives/edgar/data/1018724/000101872426000026/amzn-20260630.htm | K19: https://www.sec.gov/Archives/edgar/data/1018724/000101872426000026/amzn-20260630.htm | L19: Fact: Long-term customer commitments, primarily AWS, were approximately $496B; weighted-average remaining life was 6.4 years. Anthropic's expanded commitment is already included in the total and must not be added separately. Capex: Gross cash PP&E purchases were $54.208B, also reconciling as $98.411B first half less $44.203B Q1. Amazon's separate net cash-capex measure was $53.076B; the model preserves the gross series. | M19: AMZN-Q226-FACT | N19: AMZN-Q226-CAPEX
A20: Oracle | B20: ORCL | C20: Q2 25 | D20: FY25 Q4 | E20: 45808 | F20: 137.8 | G20: Remaining performance obligations | H20: 9.08 | I20: Cash capital expenditures; Q4 derived from annual less nine months | J20: https://www.sec.gov/Archives/edgar/data/1341439/000095017025087926/orcl-20250531.htm | K20: https://www.sec.gov/Archives/edgar/data/1341439/000095017025087926/orcl-20250531.htm | L20: Fact: Remaining performance obligations were $137.8B as of May 31, 2025. Capex: Quarter capex = $21.215B FY2025 less $12.135B first nine months = $9.080B. The $5.0B in the supplied image is not supported by Oracle's cash-flow filings. Nine-month source: https://www.sec.gov/Archives/edgar/data/1341439/000095017025037143/orcl-20250228.htm | M20: ORCL-Q225-FACT | N20: ORCL-Q225-CAPEX
A21: Oracle | B21: ORCL | C21: Q3 25 | D21: FY26 Q1 | E21: 45900 | F21: 455.3 | G21: Remaining performance obligations | H21: 8.502 | I21: Cash capital expenditures | J21: https://www.sec.gov/Archives/edgar/data/1341439/000119312525200095/orcl-20250831.htm | K21: https://www.sec.gov/Archives/edgar/data/1341439/000119312525200095/orcl-20250831.htm | L21: Fact: Remaining performance obligations were $455.3B as of August 31, 2025. Capex: The FY26 Q1 cash-flow statement reports $8.502B of capex. | M21: ORCL-Q325-FACT | N21: ORCL-Q325-CAPEX
... A29: Meta Platforms | B29: META | C29: Q2 26 | D29: Q2 2026 | E29: 46203 | F29: 60.801 | G29: Quarterly revenue | H29: 31.078 | I29: Company-defined capex including finance-lease principal payments | J29: https://www.sec.gov/Archives/edgar/data/1326801/000162828026050705/meta-20260630.htm | K29: https://www.sec.gov/Archives/edgar/data/1326801/000162828026050705/meta-20260630.htm | L29: Fact: Q2 2026 total company revenue was $60.801B; Meta does not disclose standalone AI revenue. Capex: Company-defined capex was $31.078B: $30.116B Q2 cash PP&E purchases plus $0.962B finance-lease principal, reported as $31.08B. | M29: META-Q226-FACT | N29: META-Q226-CAPEX

Sheet Sources & Notes
A1: Public Source Ledger and Model Caveats
A2: Source URLs are public. BamSEC was not available in this task, so SEC EDGAR and official company investor-relations disclosures are the authority. Model assumptions are explicitly separated from facts.
A4: Source ID | B4: Company | C4: Period | D4: Metric | E4: Value | F4: Classification | G4: Filing / Disclosure | H4: Public URL | I4: Evidence / Derivation | J4: Local Source | K4: Status | L4: Caveat
A5: MSFT-Q225-FACT | B5: Microsoft | C5: FY25 Q4 / 2025-06-30 | D5: Commercial remaining performance obligation | E5: 368 | F5: SEC filing | G5: msft-20250630.htm | H5: https://www.sec.gov/Archives/edgar/data/789019/000095017025100235/msft-20250630.htm | I5: Commercial RPO increased to $368B at June 30, 2025. | K5: Verified | L5: Fact used in model
A6: MSFT-Q225-CAPEX | B6: Microsoft | C6: FY25 Q4 / 2025-06-30 | D6: Quarterly capex | E6: 24.2 | F6: SEC filing / official company disclosure | G6: Official investor-relations disclosure | H6: https://www.microsoft.com/en-us/Investor/earnings/FY-2025-Q4/press-release-webcast | I6: Official FY25 Q4 transcript: capital expenditures were $24.2B, including finance leases. | K6: Verified | L6: Company-reported capex, including finance leases
A7: MSFT-Q325-FACT | B7: Microsoft | C7: FY26 Q1 / 2025-09-30 | D7: Commercial remaining performance obligation | E7: 392 | F7: SEC filing | G7: msft-20250930.htm | H7: https://www.sec.gov/Archives/edgar/data/789019/000119312525256321/msft-20250930.htm | I7: The 10-Q reports $398B total RPO, of which $392B is commercial RPO. | J7: 01_sources/company_filings/microsoft/Microsoft_2025-10-29_10-Q_msft-20250930.htm | K7: Verified | L7: Fact used in model
A8: MSFT-Q325-CAPEX | B8: Microsoft | C8: FY26 Q1 / 2025-09-30 | D8: Quarterly capex | E8: 34.9 | F8: SEC filing / official company disclosure | G8: Official investor-relations disclosure | H8: https://www.microsoft.com/en-us/Investor/earnings/FY-2026-Q1/press-release-webcast | I8: Official FY26 Q1 transcript: capital expenditures were $34.9B. | J8: 01_sources/company_filings/microsoft/Microsoft_2025-10-29_10-Q_msft-20250930.htm | K8: Verified | L8: Company-reported capex, including finance-lease timing effects
A9: MSFT-Q425-FACT | B9: Microsoft | C9: FY26 Q2 / 2025-12-31 | D9: Commercial remaining performance obligation | E9: 625 | F9: SEC filing | G9: msft-20251231.htm | H9: https://www.sec.gov/Archives/edgar/data/789019/000119312526027207/msft-20251231.htm | I9: Commercial RPO was $625B with a weighted-average duration of approximately 2.5 years. | J9: 01_sources/company_filings/microsoft/Microsoft_2026-01-28_10-Q_msft-20251231.htm | K9: Verified | L9: Fact used in model
A10: MSFT-Q425-CAPEX | B10: Microsoft | C10: FY26 Q2 / 2025-12-31 | D10: Quarterly capex | E10: 37.5 | F10: SEC filing / official company disclosure | G10: Official investor-relations disclosure | H10: https://www.microsoft.com/en-us/Investor/earnings/FY-2026-Q2/press-release-webcast | I10: Official FY26 Q2 transcript: capital expenditures were $37.5B. | J10: 01_sources/company_filings/microsoft/Microsoft_2026-01-28_10-Q_msft-20251231.htm | K10: Verified | L10: Company-reported capex, including finance-lease timing effects
A11: MSFT-Q126-FACT | B11: Microsoft | C11: FY26 Q3 / 2026-03-31 | D11: Commercial remaining performance obligation | E11: 627 | F11: SEC filing | G11: msft-20260331.htm | H11: https://www.sec.gov/Archives/edgar/data/789019/000119312526191507/msft-20260331.htm | I11: Commercial RPO was $627B with a weighted-average duration of approximately 2.5 years. | J11: 01_sources/company_filings/microsoft/Microsoft_2026-04-29_10-Q_msft-20260331.htm | K11: Verified | L11: Fact used in model
A12: MSFT-Q126-CAPEX | B12: Microsoft | C12: FY26 Q3 / 2026-03-31 | D12: Quarterly capex | E12: 31.9 | F12: SEC filing / official company disclosure | G12: Official investor-relations disclosure | H12: https://www.microsoft.com/en-us/Investor/earnings/FY-2026-Q3/press-release-webcast | I12: Official FY26 Q3 transcript: capital expenditures were $31.9B; cash paid for PP&E was $30.9B. | J12: 01_sources/company_filings/microsoft/Microsoft_2026-04-29_10-Q_msft-20260331.htm | K12: Verified | L12: Company-reported capex, including finance-lease timing effects
A13: MSFT-Q226-FACT | B13: Microsoft | C13: FY26 Q4 / 2026-06-30 | D13: Commercial remaining performance obligation | E13: 678 | F13: SEC filing | G13: msft-20260630.htm | H13: https://www.sec.gov/Archives/edgar/data/789019/000119312526323660/msft-20260630.htm | I13: Commercial remaining performance obligation was $678B; total company RPO was $684B. Weighted-average commercial-RPO duration including OpenAI was 2.3 years. | J13: 01_sources/company_filings/microsoft/Microsoft_2026-07-29_10-K_msft-20260630.htm | K13: Verified | L13: Fact used in model
A14: MSFT-Q226-CAPEX | B14: Microsoft | C14: FY26 Q4 / 2026-06-30 | D14: Quarterly capex | E14: 41 | F14: SEC filing / official company disclosure | G14: Official investor-relations disclosure | H14: https://www.microsoft.com/en-us/investor/events/fy-2026/earnings-fy-2026-q4 | I14: Official FY26 Q4 call reports management capex of $41.0B, including $5.6B of finance leases; cash paid for PP&E was $35.8B. The trajectory preserves Microsoft's management capex series. | J14: 01_sources/company_filings/microsoft/Microsoft_2026-07-29_10-K_msft-20260630.htm | K14: Verified | L14: Management-reported capex, including finance-lease commencement effects
A15: MSFT-PLAN | B15: Microsoft | C15: Latest snapshot | D15: Annual capex plan / guide | E15: 175 | F15: Official company outlook | G15: Official outlook | H15: https://www.microsoft.com/en-us/investor/events/fy-2026/earnings-fy-2026-q4 | I15: Microsoft reduced reported CY2026 capex expectation to approximately $175B from roughly $190B because longer datacenter useful lives shift future leases from finance leases included in its capex metric to operating leases excluded from it. Management said underlying investment expectations were unchanged; the lower denominator is a classification effect. | K15: Verified / disclosed basis | L15: CY2026 reported capex outlook after FY26 Q4 results
A16: MSFT-WACC | B16: Microsoft | C16: Latest snapshot | D16: WACC sector input | E16: 0.0934 | F16: Damodaran industry data / analyst sector selection | G16: Damodaran January 2026 data | H16: https://pages.stern.nyu.edu/~adamodar/New_Home_Page/datafile/wacc.html | I16: January 2026 cost of capital for Software (System & Application), January 2026 U.S. industry average | K16: Verified / disclosed basis | L16: Industry average, not company-specific WACC
A17: GOOG-Q225-FACT | B17: Alphabet | C17: Q2 2025 / 2025-06-30 | D17: Revenue backlog / remaining performance obligations | E17: 108.2 | F17: SEC filing | G17: goog-20250630.htm | H17: https://www.sec.gov/Archives/edgar/data/1652044/000165204425000062/goog-20250630.htm | I17: Revenue backlog/RPO was $108.2B as of June 30, 2025. | K17: Verified | L17: Fact used in model
A18: GOOG-Q225-CAPEX | B18: Alphabet | C18: Q2 2025 / 2025-06-30 | D18: Quarterly capex | E18: 22.446 | F18: SEC filing / official company disclosure | G18: goog-20250630.htm | H18: https://www.sec.gov/Archives/edgar/data/1652044/000165204425000062/goog-20250630.htm | I18: Quarter capex = $39.643B first-half cash PP&E purchases less $17.197B Q1 = $22.446B. | K18: Verified | L18: Cash purchases of property and equipment
A19: GOOG-Q325-FACT | B19: Alphabet | C19: Q3 2025 / 2025-09-30 | D19: Revenue backlog / remaining performance obligations | E19: 157.7 | F19: SEC filing | G19: goog-20250930.htm | H19: https://www.sec.gov/Archives/edgar/data/1652044/000165204425000091/goog-20250930.htm | I19: Revenue backlog/RPO was $157.7B as of September 30, 2025, primarily related to Google Cloud. | J19: 01_sources/company_filings/alphabet/Alphabet_2025-10-30_10-Q_goog-20250930.htm | K19: Verified | L19: Fact used in model
A20: GOOG-Q325-CAPEX | B20: Alphabet | C20: Q3 2025 / 2025-09-30 | D20: Quarterly capex | E20: 23.953 | F20: SEC filing / official company disclosure | G20: goog-20250930.htm | H20: https://www.sec.gov/Archives/edgar/data/1652044/000165204425000091/goog-20250930.htm | I20: Quarter capex = $63.596B nine-month cash PP&E purchases less $39.643B first half = $23.953B. | J20: 01_sources/company_filings/alphabet/Alphabet_2025-10-30_10-Q_goog-20250930.htm | K20: Verified | L20: Cash purchases of property and equipment
A21: GOOG-Q425-FACT | B21: Alphabet | C21: Q4 2025 / 2025-12-31 | D21: Revenue backlog / remaining performance obligations | E21: 242.8 | F21: SEC filing | G21: goog-20251231.htm | H21: https://www.sec.gov/Archives/edgar/data/1652044/000165204426000018/goog-20251231.htm | I21: Revenue backlog/RPO was $242.8B as of December 31, 2025, primarily related to Google Cloud. | J21: 01_sources/company_filings/alphabet/Alphabet_2026-02-05_10-K_goog-20251231.htm | K21: Verified | L21: Fact used in model
A22: GOOG-Q425-CAPEX | B22: Alphabet | C22: Q4 2025 / 2025-12-31 | D22: Quarterly capex | E22: 27.851 | F22: SEC filing / official company disclosure | G22: goog-20251231.htm | H22: https://www.sec.gov/Archives/edgar/data/1652044/000165204426000018/goog-20251231.htm | I22: Quarter capex = $91.447B FY2025 cash PP&E purchases less $63.596B first nine months = $27.851B. | J22: 01_sources/company_filings/alphabet/Alphabet_2026-02-05_10-K_goog-20251231.htm | K22: Verified | L22: Cash purchases of property and equipment
A23: GOOG-Q126-FACT | B23: Alphabet | C23: Q1 2026 / 2026-03-31 | D23: Revenue backlog / remaining performance obligations | E23: 467.6 | F23: SEC filing | G23: goog-20260331.htm | H23: https://www.sec.gov/Archives/edgar/data/1652044/000165204426000048/goog-20260331.htm | I23: Revenue backlog/RPO was $467.6B; $462.3B related to Google Cloud. Alphabet changed the definition in Q1 2026 to include original terms of one year or less ($7.3B), so the series has a comparability break. | J23: 01_sources/company_filings/alphabet/Alphabet_2026-04-30_10-Q_goog-20260331.htm | K23: Verified | L23: Fact used in model
A24: GOOG-Q126-CAPEX | B24: Alphabet | C24: Q1 2026 / 2026-03-31 | D24: Quarterly capex | E24: 35.674 | F24: SEC filing / official company disclosure | G24: goog-20260331.htm | H24: https://www.sec.gov/Archives/edgar/data/1652044/000165204426000048/goog-20260331.htm | I24: The Q1 2026 10-Q reports $35.674B of cash purchases of property and equipment. | J24: 01_sources/company_filings/alphabet/Alphabet_2026-04-30_10-Q_goog-20260331.htm | K24: Verified | L24: Cash purchases of property and equipment
A25: GOOG-Q226-FACT | B25: Alphabet | C25: Q2 2026 / 2026-06-30 | D25: Revenue backlog / remaining performance obligations | E25: 519.5 | F25: SEC filing | G25: goog-20260630.htm | H25: https://www.sec.gov/Archives/edgar/data/1652044/000165204426000071/goog-20260630.htm | I25: Revenue backlog/RPO was $519.5B, including $513.9B related to Google Cloud. The Q1 2026 short-term-contract definition change remains in effect, and Cloud backlog now includes TPU system-sale agreements; the vast majority remains GCP agreements. | J25: 01_sources/company_filings/alphabet/Alphabet_2026-07-23_10-Q_goog-20260630.htm | K25: Verified | L25: Fact used in model
A26: GOOG-Q226-CAPEX | B26: Alphabet | C26: Q2 2026 / 2026-06-30 | D26: Quarterly capex | E26: 44.924 | F26: SEC filing / official company disclosure | G26: goog-20260630.htm | H26: https://www.sec.gov/Archives/edgar/data/1652044/000165204426000071/goog-20260630.htm | I26: The Q2 2026 10-Q reports exact cash purchases of PP&E of $44.924B; narrative disclosure rounds to $44.9B. | J26: 01_sources/company_filings/alphabet/Alphabet_2026-07-23_10-Q_goog-20260630.htm | K26: Verified | L26: Cash purchases of property and equipment
A27: GOOG-PLAN | B27: Alphabet | C27: Latest snapshot | D27: Annual capex plan / guide | E27: 200 | F27: Official company outlook | G27: Official outlook | H27: https://abc.xyz/investor/events/event-details/2026/2026-Q2-Earnings-Call-2026-GgTAq7Is0z/default.aspx | I27: Alphabet's official Q2 2026 call raised its 2026 capex range to $195B-$205B from $180B-$190B. $200B is the model midpoint, not company point guidance. | K27: Verified / disclosed basis | L27: Midpoint of updated CY2026 $195B-$205B company range
A28: GOOG-WACC | B28: Alphabet | C28: Latest snapshot | D28: WACC sector input | E28: 0.1066 | F28: Damodaran industry data / analyst sector selection | G28: Damodaran January 2026 data | H28: https://pages.stern.nyu.edu/~adamodar/New_Home_Page/datafile/wacc.html | I28: January 2026 cost of capital for Software (Internet), January 2026 U.S. industry average | K28: Verified / disclosed basis | L28: Industry average, not company-specific WACC
A29: AMZN-Q225-FACT | B29: Amazon | C29: Q2 2025 / 2025-06-30 | D29: Long-term customer commitments, primarily AWS | E29: 195 | F29: SEC filing | G29: amzn-20250630.htm | H29: https://www.sec.gov/Archives/edgar/data/1018724/000101872425000086/amzn-20250630.htm | I29: Long-term customer commitments, primarily AWS, were approximately $195B as of June 30, 2025. | K29: Verified | L29: Fact used in model
A30: AMZN-Q225-CAPEX | B30: Amazon | C30: Q2 2025 / 2025-06-30 | D30: Quarterly capex | E30: 32.183 | F30: SEC filing / official company disclosure | G30: amzn-20250630.htm | H30: https://www.sec.gov/Archives/edgar/data/1018724/000101872425000086/amzn-20250630.htm | I30: SEC XBRL PaymentsToAcquireProductiveAssets for Q2 2025 was $32.183B. | K30: Verified | L30: Cash payments to acquire productive assets (SEC XBRL)
A31: AMZN-Q325-FACT | B31: Amazon | C31: Q3 2025 / 2025-09-30 | D31: Long-term customer commitments, primarily AWS | E31: 200 | F31: SEC filing | G31: amzn-20250930.htm | H31: https://www.sec.gov/Archives/edgar/data/1018724/000101872425000123/amzn-20250930.htm | I31: Long-term customer commitments, primarily AWS, were approximately $200B; weighted-average remaining life was 3.8 years. | J31: 01_sources/company_filings/amazon/Amazon_2025-10-31_10-Q_amzn-20250930.htm | K31: Verified | L31: Fact used in model
A32: AMZN-Q325-CAPEX | B32: Amazon | C32: Q3 2025 / 2025-09-30 | D32: Quarterly capex | E32: 35.095 | F32: SEC filing / official company disclosure | G32: amzn-20250930.htm | H32: https://www.sec.gov/Archives/edgar/data/1018724/000101872425000123/amzn-20250930.htm | I32: SEC XBRL PaymentsToAcquireProductiveAssets for Q3 2025 was $35.095B. | J32: 01_sources/company_filings/amazon/Amazon_2025-10-31_10-Q_amzn-20250930.htm | K32: Verified | L32: Cash payments to acquire productive assets (SEC XBRL)
A33: AMZN-Q425-FACT | B33: Amazon | C33: Q4 2025 / 2025-12-31 | D33: Long-term customer commitments, primarily AWS | E33: 244 | F33: SEC filing | G33: amzn-20251231.htm | H33: https://www.sec.gov/Archives/edgar/data/1018724/000101872426000004/amzn-20251231.htm | I33: Long-term customer commitments, primarily AWS, were approximately $244B as of December 31, 2025. | J33: 01_sources/company_filings/amazon/Amazon_2026-02-06_10-K_amzn-20251231.htm | K33: Verified | L33: Fact used in model
A34: AMZN-Q425-CAPEX | B34: Amazon | C34: Q4 2025 / 2025-12-31 | D34: Quarterly capex | E34: 39.522 | F34: SEC filing / official company disclosure | G34: amzn-20251231.htm | H34: https://www.sec.gov/Archives/edgar/data/1018724/000101872426000004/amzn-20251231.htm | I34: Quarter capex = $131.819B FY2025 less $92.297B first nine months = $39.522B. | J34: 01_sources/company_filings/amazon/Amazon_2026-02-06_10-K_amzn-20251231.htm | K34: Verified | L34: Cash payments to acquire productive assets (SEC XBRL)
A35: AMZN-Q126-FACT | B35: Amazon | C35: Q1 2026 / 2026-03-31 | D35: Long-term customer commitments, primarily AWS | E35: 364 | F35: SEC filing | G35: amzn-20260331.htm | H35: https://www.sec.gov/Archives/edgar/data/1018724/000101872426000014/amzn-20260331.htm | I35: Long-term customer commitments, primarily AWS, were approximately $364B as of March 31, 2026—not $464B as shown in the supplied snapshot. Weighted-average remaining life was 5.5 years. | J35: 01_sources/company_filings/amazon/Amazon_2026-04-30_10-Q_amzn-20260331.htm | K35: Verified | L35: Fact used in model
A36: AMZN-Q126-CAPEX | B36: Amazon | C36: Q1 2026 / 2026-03-31 | D36: Quarterly capex | E36: 44.203 | F36: SEC filing / official company disclosure | G36: amzn-20260331.htm | H36: https://www.sec.gov/Archives/edgar/data/1018724/000101872426000014/amzn-20260331.htm | I36: SEC XBRL PaymentsToAcquireProductiveAssets was $44.203B. Amazon's narrative cash-capex measure was $43.2B; this model uses the standardized XBRL series consistently across quarters. | J36: 01_sources/company_filings/amazon/Amazon_2026-04-30_10-Q_amzn-20260331.htm | K36: Verified | L36: Cash payments to acquire productive assets (SEC XBRL)
A37: AMZN-Q226-FACT | B37: Amazon | C37: Q2 2026 / 2026-06-30 | D37: Long-term customer commitments, primarily AWS | E37: 496 | F37: SEC filing | G37: amzn-20260630.htm | H37: https://www.sec.gov/Archives/edgar/data/1018724/000101872426000026/amzn-20260630.htm | I37: Long-term customer commitments, primarily AWS, were approximately $496B; weighted-average remaining life was 6.4 years. Anthropic's expanded commitment is already included in the total and must not be added separately. | J37: 01_sources/company_filings/amazon/Amazon_2026-07-31_10-Q_amzn-20260630.htm | K37: Verified | L37: Fact used in model
A38: AMZN-Q226-CAPEX | B38: Amazon | C38: Q2 2026 / 2026-06-30 | D38: Quarterly capex | E38: 54.208 | F38: SEC filing / official company disclosure | G38: amzn-20260630.htm | H38: https://www.sec.gov/Archives/edgar/data/1018724/000101872426000026/amzn-20260630.htm | I38: Gross cash PP&E purchases were $54.208B, also reconciling as $98.411B first half less $44.203B Q1. Amazon's separate net cash-capex measure was $53.076B; the model preserves the gross series. | J38: 01_sources/company_filings/amazon/Amazon_2026-07-31_10-Q_amzn-20260630.htm | K38: Verified | L38: Cash payments to acquire productive assets (SEC XBRL gross series)
A39: AMZN-PLAN | B39: Amazon | C39: Latest snapshot | D39: Annual capex plan / guide | E39: 200 | F39: Official company outlook | G39: Official outlook | H39: https://www.sec.gov/Archives/edgar/data/1018724/000101872426000002/amzn-20251231xex991.htm | I39: Amazon's SEC-filed Q4 2025 release said it expected about $200B of 2026 capex. The Q2 2026 10-Q and filed release did not provide a replacement numeric full-year plan. | K39: Verified / disclosed basis | L39: CY2026 company outlook; no replacement numeric Q2 update
A40: AMZN-WACC | B40: Amazon | C40: Latest snapshot | D40: WACC sector input | E40: 0.0727 | F40: Damodaran industry data / analyst sector selection | G40: Damodaran January 2026 data | H40: https://pages.stern.nyu.edu/~adamodar/New_Home_Page/datafile/wacc.html | I40: January 2026 cost of capital for Retail (General), January 2026 U.S. industry average | K40: Verified / disclosed basis | L40: Industry average, not company-specific WACC
A41: ORCL-Q225-FACT | B41: Oracle | C41: FY25 Q4 / 2025-05-31 | D41: Remaining performance obligations | E41: 137.8 | F41: SEC filing | G41: orcl-20250531.htm | H41: https://www.sec.gov/Archives/edgar/data/1341439/000095017025087926/orcl-20250531.htm | I41: Remaining performance obligations were $137.8B as of May 31, 2025. | K41: Verified | L41: Fact used in model
A42: ORCL-Q225-CAPEX | B42: Oracle | C42: FY25 Q4 / 2025-05-31 | D42: Quarterly capex | E42: 9.08 | F42: SEC filing / official company disclosure | G42: orcl-20250531.htm | H42: https://www.sec.gov/Archives/edgar/data/1341439/000095017025087926/orcl-20250531.htm | I42: Quarter capex = $21.215B FY2025 less $12.135B first nine months = $9.080B. The $5.0B in the supplied image is not supported by Oracle's cash-flow filings. Nine-month source: https://www.sec.gov/Archives/edgar/data/1341439/000095017025037143/orcl-20250228.htm | K42: Verified | L42: Cash capital expenditures; Q4 derived from annual less nine months
A43: ORCL-Q325-FACT | B43: Oracle | C43: FY26 Q1 / 2025-08-31 | D43: Remaining performance obligations | E43: 455.3 | F43: SEC filing | G43: orcl-20250831.htm | H43: https://www.sec.gov/Archives/edgar/data/1341439/000119312525200095/orcl-20250831.htm | I43: Remaining performance obligations were $455.3B as of August 31, 2025. | J43: 01_sources/company_filings/oracle/Oracle_2025-09-10_10-Q_orcl-20250831.htm | K43: Verified | L43: Fact used in model
A44: ORCL-Q325-CAPEX | B44: Oracle | C44: FY26 Q1 / 2025-08-31 | D44: Quarterly capex | E44: 8.502 | F44: SEC filing / official company disclosure | G44: orcl-20250831.htm | H44: https://www.sec.gov/Archives/edgar/data/1341439/000119312525200095/orcl-20250831.htm | I44: The FY26 Q1 cash-flow statement reports $8.502B of capex. | J44: 01_sources/company_filings/oracle/Oracle_2025-09-10_10-Q_orcl-20250831.htm | K44: Verified | L44: Cash capital expenditures
A45: ORCL-Q425-FACT | B45: Oracle | C45: FY26 Q2 / 2025-11-30 | D45: Remaining performance obligations | E45: 523.3 | F45: SEC filing | G45: orcl-20251130.htm | H45: https://www.sec.gov/Archives/edgar/data/1341439/000119312525315925/orcl-20251130.htm | I45: Remaining performance obligations were $523.3B as of November 30, 2025. | J45: 01_sources/company_filings/oracle/Oracle_2025-12-11_10-Q_orcl-20251130.htm | K45: Verified | L45: Fact used in model
A46: ORCL-Q425-CAPEX | B46: Oracle | C46: FY26 Q2 / 2025-11-30 | D46: Quarterly capex | E46: 12.033 | F46: SEC filing / official company disclosure | G46: orcl-20251130.htm | H46: https://www.sec.gov/Archives/edgar/data/1341439/000119312525315925/orcl-20251130.htm | I46: Quarter capex = $20.535B first half less $8.502B Q1 = $12.033B. | J46: 01_sources/company_filings/oracle/Oracle_2025-12-11_10-Q_orcl-20251130.htm | K46: Verified | L46: Cash capital expenditures; quarter derived from cumulative filing values
A47: ORCL-Q126-FACT | B47: Oracle | C47: FY26 Q3 / 2026-02-28 | D47: Remaining performance obligations | E47: 552.6 | F47: SEC filing | G47: orcl-20260228.htm | H47: https://www.sec.gov/Archives/edgar/data/1341439/000119312526101045/orcl-20260228.htm | I47: Remaining performance obligations were $552.6B as of February 28, 2026. | J47: 01_sources/company_filings/oracle/Oracle_2026-03-11_10-Q_orcl-20260228.htm | K47: Verified | L47: Fact used in model
A48: ORCL-Q126-CAPEX | B48: Oracle | C48: FY26 Q3 / 2026-02-28 | D48: Quarterly capex | E48: 18.635 | F48: SEC filing / official company disclosure | G48: orcl-20260228.htm | H48: https://www.sec.gov/Archives/edgar/data/1341439/000119312526101045/orcl-20260228.htm | I48: Quarter capex = $39.170B first nine months less $20.535B first half = $18.635B. | J48: 01_sources/company_filings/oracle/Oracle_2026-03-11_10-Q_orcl-20260228.htm | K48: Verified | L48: Cash capital expenditures; quarter derived from cumulative filing values
A49: ORCL-Q226-FACT | B49: Oracle | C49: FY26 Q4 / 2026-05-31 | D49: Remaining performance obligations | E49: 638 | F49: SEC filing | G49: orcl-20260531.htm | H49: https://www.sec.gov/Archives/edgar/data/1341439/000119312526277521/orcl-20260531.htm | I49: Remaining performance obligations were $638B at May 31, 2026, up $85B sequentially. Oracle's filed release says most Q3/Q4 RPO growth came from large AI contracts and $75B of prepaid or customer-supplied hardware reduces Oracle's own capital requirement. | J49: 01_sources/company_filings/oracle/Oracle_2026-06-22_10-K_orcl-20260531.htm | K49: Verified | L49: Fact used in model
A50: ORCL-Q226-CAPEX | B50: Oracle | C50: FY26 Q4 / 2026-05-31 | D50: Quarterly capex | E50: 16.493 | F50: SEC filing / official company disclosure | G50: orcl-20260531.htm | H50: https://www.sec.gov/Archives/edgar/data/1341439/000119312526277521/orcl-20260531.htm | I50: Quarter capex = $55.663B FY2026 cash capex less $39.170B first nine months = $16.493B. | J50: 01_sources/company_filings/oracle/Oracle_2026-06-22_10-K_orcl-20260531.htm | K50: Verified | L50: Cash capital expenditures
A51: ORCL-PLAN | B51: Oracle | C51: Latest snapshot | D51: Annual capex plan / guide | E51: 55.663 | F51: Official company outlook | G51: Official outlook | H51: https://www.sec.gov/Archives/edgar/data/1341439/000119312526265848/orcl-ex99_1.htm | I51: Oracle reported FY2026 GAAP cash capex of $55.663B. Official Q4 slides guide to approximately $70B of FY2027 net cash outlay for capex, a non-GAAP measure that deducts capex financing and customer prepayments and is not interchangeable with gross capex. The model uses the latest completed gross-capex actual rather than the expired $50B FY2026 outlook. Official slides: https://s23.q4cdn.com/440135859/files/doc_financials/2026/q4/Q4-FY26-Oracle-Earnings-Slides.pdf. Local backup: 01_sources/company_filings/oracle/Oracle_2026-06-10_Q4-FY26_Earnings_Slides.pdf | K51: Verified / disclosed basis | L51: FY2026 reported actual; no comparable FY2027 gross-capex guide
A52: ORCL-WACC | B52: Oracle | C52: Latest snapshot | D52: WACC sector input | E52: 0.0783 | F52: Damodaran industry data / analyst sector selection | G52: Damodaran January 2026 data | H52: https://pages.stern.nyu.edu/~adamodar/New_Home_Page/datafile/wacc.html | I52: January 2026 cost of capital for Computer Services, January 2026 U.S. industry average | K52: Verified / disclosed basis | L52: Industry average, not company-specific WACC
A53: META-Q225-FACT | B53: Meta Platforms | C53: Q2 2025 / 2025-06-30 | D53: Quarterly revenue | E53: 47.516 | F53: SEC filing | G53: meta-20250630.htm | H53: https://www.sec.gov/Archives/edgar/data/1326801/000162828025036791/meta-20250630.htm | I53: Q2 2025 revenue was $47.516B. | K53: Verified | L53: Fact used in model
A54: META-Q225-CAPEX | B54: Meta Platforms | C54: Q2 2025 / 2025-06-30 | D54: Quarterly capex | E54: 17.012 | F54: SEC filing / official company disclosure | G54: meta-20250630.htm | H54: https://www.sec.gov/Archives/edgar/data/1326801/000162828025036791/meta-20250630.htm | I54: Company-defined capex including finance-lease principal was $17.012B (reported as $17.01B). | K54: Verified | L54: Company-reported capex, including finance-lease principal payments
A55: META-Q325-FACT | B55: Meta Platforms | C55: Q3 2025 / 2025-09-30 | D55: Quarterly revenue | E55: 51.242 | F55: SEC filing | G55: meta-20250930.htm | H55: https://www.sec.gov/Archives/edgar/data/1326801/000162828025047240/meta-20250930.htm | I55: Q3 2025 revenue was $51.242B. | J55: 01_sources/company_filings/meta/Meta_2025-10-30_10-Q_meta-20250930.htm | K55: Verified | L55: Fact used in model
A56: META-Q325-CAPEX | B56: Meta Platforms | C56: Q3 2025 / 2025-09-30 | D56: Quarterly capex | E56: 19.374 | F56: SEC filing / official company disclosure | G56: meta-20250930.htm | H56: https://www.sec.gov/Archives/edgar/data/1326801/000162828025047240/meta-20250930.htm | I56: Company-defined capex including finance-lease principal was $19.374B (reported as $19.37B). | J56: 01_sources/company_filings/meta/Meta_2025-10-30_10-Q_meta-20250930.htm | K56: Verified | L56: Company-reported capex, including finance-lease principal payments
A57: META-Q425-FACT | B57: Meta Platforms | C57: Q4 2025 / 2025-12-31 | D57: Quarterly revenue | E57: 59.893 | F57: SEC filing | G57: meta-20251231.htm | H57: https://www.sec.gov/Archives/edgar/data/1326801/000162828026003942/meta-20251231.htm | I57: Q4 2025 revenue = $200.966B FY2025 less $141.073B first nine months = $59.893B. | J57: 01_sources/company_filings/meta/Meta_2026-01-29_10-K_meta-20251231.htm | K57: Verified | L57: Fact used in model
A58: META-Q425-CAPEX | B58: Meta Platforms | C58: Q4 2025 / 2025-12-31 | D58: Quarterly capex | E58: 22.137 | F58: SEC filing / official company disclosure | G58: meta-20251231.htm | H58: https://www.sec.gov/Archives/edgar/data/1326801/000162828026003942/meta-20251231.htm | I58: Company-defined capex including finance-lease principal was $22.137B (reported as $22.14B). | J58: 01_sources/company_filings/meta/Meta_2026-01-29_10-K_meta-20251231.htm | K58: Verified | L58: Company-reported capex, including finance-lease principal payments; derived quarter
A59: META-Q126-FACT | B59: Meta Platforms | C59: Q1 2026 / 2026-03-31 | D59: Quarterly revenue | E59: 56.311 | F59: SEC filing | G59: meta-20260331.htm | H59: https://www.sec.gov/Archives/edgar/data/1326801/000162828026028526/meta-20260331.htm | I59: Q1 2026 revenue was $56.311B. The $240B annualized revenue in the supplied snapshot is based on roughly $60B and does not match the Q1 filing; filing-based annualized revenue is $225.244B. | J59: 01_sources/company_filings/meta/Meta_2026-04-30_10-Q_meta-20260331.htm | K59: Verified | L59: Fact used in model
A60: META-Q126-CAPEX | B60: Meta Platforms | C60: Q1 2026 / 2026-03-31 | D60: Quarterly capex | E60: 19.84 | F60: SEC filing / official company disclosure | G60: meta-20260331.htm | H60: https://www.sec.gov/Archives/edgar/data/1326801/000162828026028526/meta-20260331.htm | I60: Company-defined capex was $19.840B: $18.997B cash PP&E purchases plus $0.843B finance-lease principal. | J60: 01_sources/company_filings/meta/Meta_2026-04-30_10-Q_meta-20260331.htm | K60: Verified | L60: Company-reported capex, including finance-lease principal payments
A61: META-Q226-FACT | B61: Meta Platforms | C61: Q2 2026 / 2026-06-30 | D61: Quarterly revenue | E61: 60.801 | F61: SEC filing | G61: meta-20260630.htm | H61: https://www.sec.gov/Archives/edgar/data/1326801/000162828026050705/meta-20260630.htm | I61: Q2 2026 total company revenue was $60.801B; Meta does not disclose standalone AI revenue. | J61: 01_sources/company_filings/meta/Meta_2026-07-30_10-Q_meta-20260630.htm | K61: Verified | L61: Fact used in model
A62: META-Q226-CAPEX | B62: Meta Platforms | C62: Q2 2026 / 2026-06-30 | D62: Quarterly capex | E62: 31.078 | F62: SEC filing / official company disclosure | G62: meta-20260630.htm | H62: https://www.sec.gov/Archives/edgar/data/1326801/000162828026050705/meta-20260630.htm | I62: Company-defined capex was $31.078B: $30.116B Q2 cash PP&E purchases plus $0.962B finance-lease principal, reported as $31.08B. | J62: 01_sources/company_filings/meta/Meta_2026-07-30_10-Q_meta-20260630.htm | K62: Verified | L62: Company-defined capex including finance-lease principal payments
A63: META-PLAN | B63: Meta Platforms | C63: Latest snapshot | D63: Annual capex plan / guide | E63: 137.5 | F63: Official company outlook | G63: Official outlook | H63: https://www.sec.gov/Archives/edgar/data/1326801/000162828026050596/meta-06302026xexhibit991.htm | I63: Meta narrowed 2026 capex guidance to $130B-$145B from $125B-$145B. $137.5B is the model midpoint, not company point guidance. | K63: Verified / disclosed basis | L63: Midpoint of narrowed CY2026 $130B-$145B company range
A64: META-WACC | B64: Meta Platforms | C64: Latest snapshot | D64: WACC sector input | E64: 0.1066 | F64: Damodaran industry data / analyst sector selection | G64: Damodaran January 2026 data | H64: https://pages.stern.nyu.edu/~adamodar/New_Home_Page/datafile/wacc.html | I64: January 2026 cost of capital for Software (Internet), January 2026 U.S. industry average | K64: Verified / disclosed basis | L64: Industry average, not company-specific WACC
A67: Critical Interpretation and Comparability Caveats
A68: • This is a proxy model, not an accounting ROIC calculation. RPO/backlog is converted into an annualized revenue proxy using assumed AI attribution and duration.
A69: • Five quarters are shown so the change row is a true Q2 2025-to-Q2 2026 comparison. The original model assumptions are held constant to isolate reported-financial movement.
A70: • RPO/backlog is not like-for-like: Microsoft uses commercial RPO; Alphabet's definition changed in Q1 2026 and now includes TPU system-sale agreements; Amazon reports primarily AWS commitments; Oracle reports company-wide RPO.
A71: • Current disclosed durations differ from the retained assumptions: Microsoft disclosed 2.3 years versus the model's 2.5; Amazon disclosed 6.4 years versus the model's 4.0. These differences can materially change the revenue proxy.
A72: • Capex definitions differ by issuer. Microsoft uses a management measure affected by lease classification; Alphabet and Oracle use cash PP&E/capex; Amazon uses gross productive-asset cash payments; Meta includes finance-lease principal.
A73: • Microsoft's $175B reported capex outlook is lower because leases shifted outside its metric, not because economic investment plans fell. Alphabet and Meta denominators are range midpoints. Oracle uses FY2026 gross-capex actual because its approximately $70B FY2027 outlook is a non-comparable net-cash-outlay measure.
A74: • AI shares of RPO/revenue and capex, NOPAT margins, duration assumptions, and Damodaran sector mappings are analyst assumptions. Spread is percentage points; only the Q2-to-Q2 change row is basis points.

Sheet Checks
A1: Independent Recalculation Checks
A3: Check ID | B3: Test | C3: Expected | D3: Workbook Value | E3: Tolerance | F3: Status
A4: MSFT-Q225-ANNUALIZED-AI-CAPEX | B4: MSFT Q2 25 Annualized AI capex | C4: 82.28 | D4: =Trajectory!C7 -> 82.28 | E4: 1e-08 | F4: =IF(ABS(C4-D4)<=E4,"PASS","FAIL") -> PASS
A5: MSFT-Q225-ANNUALIZED-AI-REVENUE | B5: MSFT Q2 25 Annualized AI revenue | C5: 73.6 | D5: =Trajectory!C8 -> 73.6 | E5: 1e-08 | F5: =IF(ABS(C5-D5)<=E5,"PASS","FAIL") -> PASS
A6: MSFT-Q225-FORWARD-ROIC | B6: MSFT Q2 25 Forward ROIC | C6: 0.26835197 | D6: =Trajectory!C9 -> 0.26835197 | E6: 1e-10 | F6: =IF(ABS(C6-D6)<=E6,"PASS","FAIL") -> PASS
A7: MSFT-Q225-SPREAD | B7: MSFT Q2 25 Spread | C7: 0.17495197 | D7: =Trajectory!C10 -> 0.17495197 | E7: 1e-10 | F7: =IF(ABS(C7-D7)<=E7,"PASS","FAIL") -> PASS
A8: MSFT-Q325-ANNUALIZED-AI-CAPEX | B8: MSFT Q3 25 Annualized AI capex | C8: 118.66 | D8: =Trajectory!D7 -> 118.66 | E8: 1e-08 | F8: =IF(ABS(C8-D8)<=E8,"PASS","FAIL") -> PASS
A9: MSFT-Q325-ANNUALIZED-AI-REVENUE | B9: MSFT Q3 25 Annualized AI revenue | C9: 78.4 | D9: =Trajectory!D8 -> 78.4 | E9: 1e-08 | F9: =IF(ABS(C9-D9)<=E9,"PASS","FAIL") -> PASS
A10: MSFT-Q325-FORWARD-ROIC | B10: MSFT Q3 25 Forward ROIC | C10: 0.19821338 | D10: =Trajectory!D9 -> 0.19821338 | E10: 1e-10 | F10: =IF(ABS(C10-D10)<=E10,"PASS","FAIL") -> PASS
A11: MSFT-Q325-SPREAD | B11: MSFT Q3 25 Spread | C11: 0.10481338 | D11: =Trajectory!D10 -> 0.10481338 | E11: 1e-10 | F11: =IF(ABS(C11-D11)<=E11,"PASS","FAIL") -> PASS
A12: MSFT-Q425-ANNUALIZED-AI-CAPEX | B12: MSFT Q4 25 Annualized AI capex | C12: 127.5 | D12: =Trajectory!E7 -> 127.5 | E12: 1e-08 | F12: =IF(ABS(C12-D12)<=E12,"PASS","FAIL") -> PASS
A13: MSFT-Q425-ANNUALIZED-AI-REVENUE | B13: MSFT Q4 25 Annualized AI revenue | C13: 125 | D13: =Trajectory!E8 -> 125 | E13: 1e-08 | F13: =IF(ABS(C13-D13)<=E13,"PASS","FAIL") -> PASS
A14: MSFT-Q425-FORWARD-ROIC | B14: MSFT Q4 25 Forward ROIC | C14: 0.29411765 | D14: =Trajectory!E9 -> 0.29411765 | E14: 1e-10 | F14: =IF(ABS(C14-D14)<=E14,"PASS","FAIL") -> PASS
A15: MSFT-Q425-SPREAD | B15: MSFT Q4 25 Spread | C15: 0.20071765 | D15: =Trajectory!E10 -> 0.20071765 | E15: 1e-10 | F15: =IF(ABS(C15-D15)<=E15,"PASS","FAIL") -> PASS
A16: MSFT-Q126-ANNUALIZED-AI-CAPEX | B16: MSFT Q1 26 Annualized AI capex | C16: 108.46 | D16: =Trajectory!F7 -> 108.46 | E16: 1e-08 | F16: =IF(ABS(C16-D16)<=E16,"PASS","FAIL") -> PASS
A17: MSFT-Q126-ANNUALIZED-AI-REVENUE | B17: MSFT Q1 26 Annualized AI revenue | C17: 125.4 | D17: =Trajectory!F8 -> 125.4 | E17: 1e-08 | F17: =IF(ABS(C17-D17)<=E17,"PASS","FAIL") -> PASS
A18: MSFT-Q126-FORWARD-ROIC | B18: MSFT Q1 26 Forward ROIC | C18: 0.34685598 | D18: =Trajectory!F9 -> 0.34685598 | E18: 1e-10 | F18: =IF(ABS(C18-D18)<=E18,"PASS","FAIL") -> PASS
A19: MSFT-Q126-SPREAD | B19: MSFT Q1 26 Spread | C19: 0.25345598 | D19: =Trajectory!F10 -> 0.25345598 | E19: 1e-10 | F19: =IF(ABS(C19-D19)<=E19,"PASS","FAIL") -> PASS
A20: MSFT-Q226-ANNUALIZED-AI-CAPEX | B20: MSFT Q2 26 Annualized AI capex | C20: 139.4 | D20: =Trajectory!G7 -> 139.4 | E20: 1e-08 | F20: =IF(ABS(C20-D20)<=E20,"PASS","FAIL") -> PASS
A21: MSFT-Q226-ANNUALIZED-AI-REVENUE | B21: MSFT Q2 26 Annualized AI revenue | C21: 135.6 | D21: =Trajectory!G8 -> 135.6 | E21: 1e-08 | F21: =IF(ABS(C21-D21)<=E21,"PASS","FAIL") -> PASS
A22: MSFT-Q226-FORWARD-ROIC | B22: MSFT Q2 26 Forward ROIC | C22: 0.29182209 | D22: =Trajectory!G9 -> 0.29182209 | E22: 1e-10 | F22: =IF(ABS(C22-D22)<=E22,"PASS","FAIL") -> PASS
A23: MSFT-Q226-SPREAD | B23: MSFT Q2 26 Spread | C23: 0.19842209 | D23: =Trajectory!G10 -> 0.19842209 | E23: 1e-10 | F23: =IF(ABS(C23-D23)<=E23,"PASS","FAIL") -> PASS
A24: MSFT-SNAPSHOT-ANNUALIZED-AI-REVENUE | B24: MSFT Snapshot annualized AI revenue | C24: 135.6 | D24: =Snapshot!B14 -> 135.6 | E24: 1e-08 | F24: =IF(ABS(C24-D24)<=E24,"PASS","FAIL") -> PASS
A25: MSFT-SNAPSHOT-AI-CAPEX | B25: MSFT Snapshot AI capex | C25: 148.75 | D25: =Snapshot!B12 -> 148.75 | E25: 1e-08 | F25: =IF(ABS(C25-D25)<=E25,"PASS","FAIL") -> PASS
A26: MSFT-SNAPSHOT-BASE-ROIC | B26: MSFT Snapshot base ROIC | C26: 0.27347899 | D26: =Snapshot!B17 -> 0.27347899 | E26: 1e-10 | F26: =IF(ABS(C26-D26)<=E26,"PASS","FAIL") -> PASS
A27: MSFT-SNAPSHOT-BASE-SPREAD | B27: MSFT Snapshot base spread | C27: 0.18007899 | D27: =Snapshot!B19 -> 0.18007899 | E27: 1e-10 | F27: =IF(ABS(C27-D27)<=E27,"PASS","FAIL") -> PASS
A28: MSFT-SNAPSHOT-BEAR-SPREAD | B28: MSFT Snapshot bear spread | C28: 0.088919328 | D28: =Snapshot!B21 -> 0.088919328 | E28: 1e-10 | F28: =IF(ABS(C28-D28)<=E28,"PASS","FAIL") -> PASS
A29: MSFT-SNAPSHOT-BULL-SPREAD | B29: MSFT Snapshot bull spread | C29: 0.27123866 | D29: =Snapshot!B23 -> 0.27123866 | E29: 1e-10 | F29: =IF(ABS(C29-D29)<=E29,"PASS","FAIL") -> PASS
A30: MSFT-DELTA-SPREAD-BPS | B30: MSFT displayed-window spread change in bps | C30: 234.70126 | D30: =Snapshot!B27 -> 234.70126 | E30: 0.01 | F30: =IF(ABS(C30-D30)<=E30,"PASS","FAIL") -> PASS
A31: GOOG-Q225-ANNUALIZED-AI-CAPEX | B31: GOOG Q2 25 Annualized AI capex | C31: 71.8272 | D31: =Trajectory!C14 -> 71.8272 | E31: 1e-08 | F31: =IF(ABS(C31-D31)<=E31,"PASS","FAIL") -> PASS
A32: GOOG-Q225-ANNUALIZED-AI-REVENUE | B32: GOOG Q2 25 Annualized AI revenue | C32: 28.132 | D32: =Trajectory!C15 -> 28.132 | E32: 1e-08 | F32: =IF(ABS(C32-D32)<=E32,"PASS","FAIL") -> PASS
A33: GOOG-Q225-FORWARD-ROIC | B33: GOOG Q2 25 Forward ROIC | C33: 0.11749866 | D33: =Trajectory!C16 -> 0.11749866 | E33: 1e-10 | F33: =IF(ABS(C33-D33)<=E33,"PASS","FAIL") -> PASS
A34: GOOG-Q225-SPREAD | B34: GOOG Q2 25 Spread | C34: 0.010898663 | D34: =Trajectory!C17 -> 0.010898663 | E34: 1e-10 | F34: =IF(ABS(C34-D34)<=E34,"PASS","FAIL") -> PASS
A35: GOOG-Q325-ANNUALIZED-AI-CAPEX | B35: GOOG Q3 25 Annualized AI capex | C35: 76.6496 | D35: =Trajectory!D14 -> 76.6496 | E35: 1e-08 | F35: =IF(ABS(C35-D35)<=E35,"PASS","FAIL") -> PASS
A36: GOOG-Q325-ANNUALIZED-AI-REVENUE | B36: GOOG Q3 25 Annualized AI revenue | C36: 41.002 | D36: =Trajectory!D15 -> 41.002 | E36: 1e-08 | F36: =IF(ABS(C36-D36)<=E36,"PASS","FAIL") -> PASS
A37: GOOG-Q325-FORWARD-ROIC | B37: GOOG Q3 25 Forward ROIC | C37: 0.16047833 | D37: =Trajectory!D16 -> 0.16047833 | E37: 1e-10 | F37: =IF(ABS(C37-D37)<=E37,"PASS","FAIL") -> PASS
A38: GOOG-Q325-SPREAD | B38: GOOG Q3 25 Spread | C38: 0.053878333 | D38: =Trajectory!D17 -> 0.053878333 | E38: 1e-10 | F38: =IF(ABS(C38-D38)<=E38,"PASS","FAIL") -> PASS
A39: GOOG-Q425-ANNUALIZED-AI-CAPEX | B39: GOOG Q4 25 Annualized AI capex | C39: 89.1232 | D39: =Trajectory!E14 -> 89.1232 | E39: 1e-08 | F39: =IF(ABS(C39-D39)<=E39,"PASS","FAIL") -> PASS
A40: GOOG-Q425-ANNUALIZED-AI-REVENUE | B40: GOOG Q4 25 Annualized AI revenue | C40: 63.128 | D40: =Trajectory!E15 -> 63.128 | E40: 1e-08 | F40: =IF(ABS(C40-D40)<=E40,"PASS","FAIL") -> PASS
A41: GOOG-Q425-FORWARD-ROIC | B41: GOOG Q4 25 Forward ROIC | C41: 0.21249686 | D41: =Trajectory!E16 -> 0.21249686 | E41: 1e-10 | F41: =IF(ABS(C41-D41)<=E41,"PASS","FAIL") -> PASS
A42: GOOG-Q425-SPREAD | B42: GOOG Q4 25 Spread | C42: 0.10589686 | D42: =Trajectory!E17 -> 0.10589686 | E42: 1e-10 | F42: =IF(ABS(C42-D42)<=E42,"PASS","FAIL") -> PASS
A43: GOOG-Q126-ANNUALIZED-AI-CAPEX | B43: GOOG Q1 26 Annualized AI capex | C43: 114.1568 | D43: =Trajectory!F14 -> 114.1568 | E43: 1e-08 | F43: =IF(ABS(C43-D43)<=E43,"PASS","FAIL") -> PASS
A44: GOOG-Q126-ANNUALIZED-AI-REVENUE | B44: GOOG Q1 26 Annualized AI revenue | C44: 121.576 | D44: =Trajectory!F15 -> 121.576 | E44: 1e-08 | F44: =IF(ABS(C44-D44)<=E44,"PASS","FAIL") -> PASS
A45: GOOG-Q126-FORWARD-ROIC | B45: GOOG Q1 26 Forward ROIC | C45: 0.31949739 | D45: =Trajectory!F16 -> 0.31949739 | E45: 1e-10 | F45: =IF(ABS(C45-D45)<=E45,"PASS","FAIL") -> PASS
A46: GOOG-Q126-SPREAD | B46: GOOG Q1 26 Spread | C46: 0.21289739 | D46: =Trajectory!F17 -> 0.21289739 | E46: 1e-10 | F46: =IF(ABS(C46-D46)<=E46,"PASS","FAIL") -> PASS
A47: GOOG-Q226-ANNUALIZED-AI-CAPEX | B47: GOOG Q2 26 Annualized AI capex | C47: 143.7568 | D47: =Trajectory!G14 -> 143.7568 | E47: 1e-08 | F47: =IF(ABS(C47-D47)<=E47,"PASS","FAIL") -> PASS
A48: GOOG-Q226-ANNUALIZED-AI-REVENUE | B48: GOOG Q2 26 Annualized AI revenue | C48: 135.07 | D48: =Trajectory!G15 -> 135.07 | E48: 1e-08 | F48: =IF(ABS(C48-D48)<=E48,"PASS","FAIL") -> PASS
A49: GOOG-Q226-FORWARD-ROIC | B49: GOOG Q2 26 Forward ROIC | C49: 0.28187188 | D49: =Trajectory!G16 -> 0.28187188 | E49: 1e-10 | F49: =IF(ABS(C49-D49)<=E49,"PASS","FAIL") -> PASS
A50: GOOG-Q226-SPREAD | B50: GOOG Q2 26 Spread | C50: 0.17527188 | D50: =Trajectory!G17 -> 0.17527188 | E50: 1e-10 | F50: =IF(ABS(C50-D50)<=E50,"PASS","FAIL") -> PASS
A51: GOOG-SNAPSHOT-ANNUALIZED-AI-REVENUE | B51: GOOG Snapshot annualized AI revenue | C51: 135.07 | D51: =Snapshot!C14 -> 135.07 | E51: 1e-08 | F51: =IF(ABS(C51-D51)<=E51,"PASS","FAIL") -> PASS
A52: GOOG-SNAPSHOT-AI-CAPEX | B52: GOOG Snapshot AI capex | C52: 160 | D52: =Snapshot!C12 -> 160 | E52: 1e-08 | F52: =IF(ABS(C52-D52)<=E52,"PASS","FAIL") -> PASS
A53: GOOG-SNAPSHOT-BASE-ROIC | B53: GOOG Snapshot base ROIC | C53: 0.25325625 | D53: =Snapshot!C17 -> 0.25325625 | E53: 1e-10 | F53: =IF(ABS(C53-D53)<=E53,"PASS","FAIL") -> PASS
A54: GOOG-SNAPSHOT-BASE-SPREAD | B54: GOOG Snapshot base spread | C54: 0.14665625 | D54: =Snapshot!C19 -> 0.14665625 | E54: 1e-10 | F54: =IF(ABS(C54-D54)<=E54,"PASS","FAIL") -> PASS
A55: GOOG-SNAPSHOT-BEAR-SPREAD | B55: GOOG Snapshot bear spread | C55: 0.0622375 | D55: =Snapshot!C21 -> 0.0622375 | E55: 1e-10 | F55: =IF(ABS(C55-D55)<=E55,"PASS","FAIL") -> PASS
A56: GOOG-SNAPSHOT-BULL-SPREAD | B56: GOOG Snapshot bull spread | C56: 0.231075 | D56: =Snapshot!C23 -> 0.231075 | E56: 1e-10 | F56: =IF(ABS(C56-D56)<=E56,"PASS","FAIL") -> PASS
A57: GOOG-DELTA-SPREAD-BPS | B57: GOOG displayed-window spread change in bps | C57: 1643.7322 | D57: =Snapshot!C27 -> 1643.7322 | E57: 0.01 | F57: =IF(ABS(C57-D57)<=E57,"PASS","FAIL") -> PASS
A58: AMZN-Q225-ANNUALIZED-AI-CAPEX | B58: AMZN Q2 25 Annualized AI capex | C58: 96.549 | D58: =Trajectory!C21 -> 96.549 | E58: 1e-08 | F58: =IF(ABS(C58-D58)<=E58,"PASS","FAIL") -> PASS
A59: AMZN-Q225-ANNUALIZED-AI-REVENUE | B59: AMZN Q2 25 Annualized AI revenue | C59: 26.8125 | D59: =Trajectory!C22 -> 26.8125 | E59: 1e-08 | F59: =IF(ABS(C59-D59)<=E59,"PASS","FAIL") -> PASS
A60: AMZN-Q225-FORWARD-ROIC | B60: AMZN Q2 25 Forward ROIC | C60: 0.077758444 | D60: =Trajectory!C23 -> 0.077758444 | E60: 1e-10 | F60: =IF(ABS(C60-D60)<=E60,"PASS","FAIL") -> PASS
A61: AMZN-Q225-SPREAD | B61: AMZN Q2 25 Spread | C61: 0.0050584439 | D61: =Trajectory!C24 -> 0.0050584439 | E61: 1e-10 | F61: =IF(ABS(C61-D61)<=E61,"PASS","FAIL") -> PASS
A62: AMZN-Q325-ANNUALIZED-AI-CAPEX | B62: AMZN Q3 25 Annualized AI capex | C62: 105.285 | D62: =Trajectory!D21 -> 105.285 | E62: 1e-08 | F62: =IF(ABS(C62-D62)<=E62,"PASS","FAIL") -> PASS
A63: AMZN-Q325-ANNUALIZED-AI-REVENUE | B63: AMZN Q3 25 Annualized AI revenue | C63: 27.5 | D63: =Trajectory!D22 -> 27.5 | E63: 1e-08 | F63: =IF(ABS(C63-D63)<=E63,"PASS","FAIL") -> PASS
A64: AMZN-Q325-FORWARD-ROIC | B64: AMZN Q3 25 Forward ROIC | C64: 0.073134825 | D64: =Trajectory!D23 -> 0.073134825 | E64: 1e-10 | F64: =IF(ABS(C64-D64)<=E64,"PASS","FAIL") -> PASS
A65: AMZN-Q325-SPREAD | B65: AMZN Q3 25 Spread | C65: 0.00043482452 | D65: =Trajectory!D24 -> 0.00043482452 | E65: 1e-10 | F65: =IF(ABS(C65-D65)<=E65,"PASS","FAIL") -> PASS
A66: AMZN-Q425-ANNUALIZED-AI-CAPEX | B66: AMZN Q4 25 Annualized AI capex | C66: 118.566 | D66: =Trajectory!E21 -> 118.566 | E66: 1e-08 | F66: =IF(ABS(C66-D66)<=E66,"PASS","FAIL") -> PASS
A67: AMZN-Q425-ANNUALIZED-AI-REVENUE | B67: AMZN Q4 25 Annualized AI revenue | C67: 33.55 | D67: =Trajectory!E22 -> 33.55 | E67: 1e-08 | F67: =IF(ABS(C67-D67)<=E67,"PASS","FAIL") -> PASS
A68: AMZN-Q425-FORWARD-ROIC | B68: AMZN Q4 25 Forward ROIC | C68: 0.079230133 | D68: =Trajectory!E23 -> 0.079230133 | E68: 1e-10 | F68: =IF(ABS(C68-D68)<=E68,"PASS","FAIL") -> PASS
A69: AMZN-Q425-SPREAD | B69: AMZN Q4 25 Spread | C69: 0.0065301334 | D69: =Trajectory!E24 -> 0.0065301334 | E69: 1e-10 | F69: =IF(ABS(C69-D69)<=E69,"PASS","FAIL") -> PASS
A70: AMZN-Q126-ANNUALIZED-AI-CAPEX | B70: AMZN Q1 26 Annualized AI capex | C70: 132.609 | D70: =Trajectory!F21 -> 132.609 | E70: 1e-08 | F70: =IF(ABS(C70-D70)<=E70,"PASS","FAIL") -> PASS
A71: AMZN-Q126-ANNUALIZED-AI-REVENUE | B71: AMZN Q1 26 Annualized AI revenue | C71: 50.05 | D71: =Trajectory!F22 -> 50.05 | E71: 1e-08 | F71: =IF(ABS(C71-D71)<=E71,"PASS","FAIL") -> PASS
A72: AMZN-Q126-FORWARD-ROIC | B72: AMZN Q1 26 Forward ROIC | C72: 0.1056791 | D72: =Trajectory!F23 -> 0.1056791 | E72: 1e-10 | F72: =IF(ABS(C72-D72)<=E72,"PASS","FAIL") -> PASS
A73: AMZN-Q126-SPREAD | B73: AMZN Q1 26 Spread | C73: 0.032979102 | D73: =Trajectory!F24 -> 0.032979102 | E73: 1e-10 | F73: =IF(ABS(C73-D73)<=E73,"PASS","FAIL") -> PASS
A74: AMZN-Q226-ANNUALIZED-AI-CAPEX | B74: AMZN Q2 26 Annualized AI capex | C74: 162.624 | D74: =Trajectory!G21 -> 162.624 | E74: 1e-08 | F74: =IF(ABS(C74-D74)<=E74,"PASS","FAIL") -> PASS
A75: AMZN-Q226-ANNUALIZED-AI-REVENUE | B75: AMZN Q2 26 Annualized AI revenue | C75: 68.2 | D75: =Trajectory!G22 -> 68.2 | E75: 1e-08 | F75: =IF(ABS(C75-D75)<=E75,"PASS","FAIL") -> PASS
A76: AMZN-Q226-FORWARD-ROIC | B76: AMZN Q2 26 Forward ROIC | C76: 0.11742424 | D76: =Trajectory!G23 -> 0.11742424 | E76: 1e-10 | F76: =IF(ABS(C76-D76)<=E76,"PASS","FAIL") -> PASS
A77: AMZN-Q226-SPREAD | B77: AMZN Q2 26 Spread | C77: 0.044724242 | D77: =Trajectory!G24 -> 0.044724242 | E77: 1e-10 | F77: =IF(ABS(C77-D77)<=E77,"PASS","FAIL") -> PASS
A78: AMZN-SNAPSHOT-ANNUALIZED-AI-REVENUE | B78: AMZN Snapshot annualized AI revenue | C78: 68.2 | D78: =Snapshot!D14 -> 68.2 | E78: 1e-08 | F78: =IF(ABS(C78-D78)<=E78,"PASS","FAIL") -> PASS
A79: AMZN-SNAPSHOT-AI-CAPEX | B79: AMZN Snapshot AI capex | C79: 150 | D79: =Snapshot!D12 -> 150 | E79: 1e-08 | F79: =IF(ABS(C79-D79)<=E79,"PASS","FAIL") -> PASS
A80: AMZN-SNAPSHOT-BASE-ROIC | B80: AMZN Snapshot base ROIC | C80: 0.12730667 | D80: =Snapshot!D17 -> 0.12730667 | E80: 1e-10 | F80: =IF(ABS(C80-D80)<=E80,"PASS","FAIL") -> PASS
A81: AMZN-SNAPSHOT-BASE-SPREAD | B81: AMZN Snapshot base spread | C81: 0.054606667 | D81: =Snapshot!D19 -> 0.054606667 | E81: 1e-10 | F81: =IF(ABS(C81-D81)<=E81,"PASS","FAIL") -> PASS
A82: AMZN-SNAPSHOT-BEAR-SPREAD | B82: AMZN Snapshot bear spread | C82: 0.018233333 | D82: =Snapshot!D21 -> 0.018233333 | E82: 1e-10 | F82: =IF(ABS(C82-D82)<=E82,"PASS","FAIL") -> PASS
A83: AMZN-SNAPSHOT-BULL-SPREAD | B83: AMZN Snapshot bull spread | C83: 0.10007333 | D83: =Snapshot!D23 -> 0.10007333 | E83: 1e-10 | F83: =IF(ABS(C83-D83)<=E83,"PASS","FAIL") -> PASS
A84: AMZN-DELTA-SPREAD-BPS | B84: AMZN displayed-window spread change in bps | C84: 396.65799 | D84: =Snapshot!D27 -> 396.65799 | E84: 0.01 | F84: =IF(ABS(C84-D84)<=E84,"PASS","FAIL") -> PASS
A85: ORCL-Q225-ANNUALIZED-AI-CAPEX | B85: ORCL Q2 25 Annualized AI capex | C85: 32.688 | D85: =Trajectory!C28 -> 32.688 | E85: 1e-08 | F85: =IF(ABS(C85-D85)<=E85,"PASS","FAIL") -> PASS
A86: ORCL-Q225-ANNUALIZED-AI-REVENUE | B86: ORCL Q2 25 Annualized AI revenue | C86: 23.426 | D86: =Trajectory!C29 -> 23.426 | E86: 1e-08 | F86: =IF(ABS(C86-D86)<=E86,"PASS","FAIL") -> PASS
A87: ORCL-Q225-FORWARD-ROIC | B87: ORCL Q2 25 Forward ROIC | C87: 0.1289978 | D87: =Trajectory!C30 -> 0.1289978 | E87: 1e-10 | F87: =IF(ABS(C87-D87)<=E87,"PASS","FAIL") -> PASS
A88: ORCL-Q225-SPREAD | B88: ORCL Q2 25 Spread | C88: 0.050697797 | D88: =Trajectory!C31 -> 0.050697797 | E88: 1e-10 | F88: =IF(ABS(C88-D88)<=E88,"PASS","FAIL") -> PASS
A89: ORCL-Q325-ANNUALIZED-AI-CAPEX | B89: ORCL Q3 25 Annualized AI capex | C89: 30.6072 | D89: =Trajectory!D28 -> 30.6072 | E89: 1e-08 | F89: =IF(ABS(C89-D89)<=E89,"PASS","FAIL") -> PASS
A90: ORCL-Q325-ANNUALIZED-AI-REVENUE | B90: ORCL Q3 25 Annualized AI revenue | C90: 77.401 | D90: =Trajectory!D29 -> 77.401 | E90: 1e-08 | F90: =IF(ABS(C90-D90)<=E90,"PASS","FAIL") -> PASS
A91: ORCL-Q325-FORWARD-ROIC | B91: ORCL Q3 25 Forward ROIC | C91: 0.4551929 | D91: =Trajectory!D30 -> 0.4551929 | E91: 1e-10 | F91: =IF(ABS(C91-D91)<=E91,"PASS","FAIL") -> PASS
A92: ORCL-Q325-SPREAD | B92: ORCL Q3 25 Spread | C92: 0.3768929 | D92: =Trajectory!D31 -> 0.3768929 | E92: 1e-10 | F92: =IF(ABS(C92-D92)<=E92,"PASS","FAIL") -> PASS
A93: ORCL-Q425-ANNUALIZED-AI-CAPEX | B93: ORCL Q4 25 Annualized AI capex | C93: 43.3188 | D93: =Trajectory!E28 -> 43.3188 | E93: 1e-08 | F93: =IF(ABS(C93-D93)<=E93,"PASS","FAIL") -> PASS
A94: ORCL-Q425-ANNUALIZED-AI-REVENUE | B94: ORCL Q4 25 Annualized AI revenue | C94: 88.961 | D94: =Trajectory!E29 -> 88.961 | E94: 1e-08 | F94: =IF(ABS(C94-D94)<=E94,"PASS","FAIL") -> PASS
A95: ORCL-Q425-FORWARD-ROIC | B95: ORCL Q4 25 Forward ROIC | C95: 0.36965428 | D95: =Trajectory!E30 -> 0.36965428 | E95: 1e-10 | F95: =IF(ABS(C95-D95)<=E95,"PASS","FAIL") -> PASS
A96: ORCL-Q425-SPREAD | B96: ORCL Q4 25 Spread | C96: 0.29135428 | D96: =Trajectory!E31 -> 0.29135428 | E96: 1e-10 | F96: =IF(ABS(C96-D96)<=E96,"PASS","FAIL") -> PASS
A97: ORCL-Q126-ANNUALIZED-AI-CAPEX | B97: ORCL Q1 26 Annualized AI capex | C97: 67.086 | D97: =Trajectory!F28 -> 67.086 | E97: 1e-08 | F97: =IF(ABS(C97-D97)<=E97,"PASS","FAIL") -> PASS
A98: ORCL-Q126-ANNUALIZED-AI-REVENUE | B98: ORCL Q1 26 Annualized AI revenue | C98: 93.942 | D98: =Trajectory!F29 -> 93.942 | E98: 1e-08 | F98: =IF(ABS(C98-D98)<=E98,"PASS","FAIL") -> PASS
A99: ORCL-Q126-FORWARD-ROIC | B99: ORCL Q1 26 Forward ROIC | C99: 0.25205796 | D99: =Trajectory!F30 -> 0.25205796 | E99: 1e-10 | F99: =IF(ABS(C99-D99)<=E99,"PASS","FAIL") -> PASS
A100: ORCL-Q126-SPREAD | B100: ORCL Q1 26 Spread | C100: 0.17375796 | D100: =Trajectory!F31 -> 0.17375796 | E100: 1e-10 | F100: =IF(ABS(C100-D100)<=E100,"PASS","FAIL") -> PASS
A101: ORCL-Q226-ANNUALIZED-AI-CAPEX | B101: ORCL Q2 26 Annualized AI capex | C101: 59.3748 | D101: =Trajectory!G28 -> 59.3748 | E101: 1e-08 | F101: =IF(ABS(C101-D101)<=E101,"PASS","FAIL") -> PASS
...
